{"origin":"BSB","generated":"2026-06-24T06:33:35.223Z","count":72,"routes":{"BHZ":{"origin":"BSB","destination":"BHZ","bestDeparture":"2026-10-12","bestBooking":"2026-06-24","priceBase":31,"low":31,"lowDate":"2026-06-24","dropAbs":4,"dropPct":11,"currency":"EUR","airline":"","confidence":"high","book":"https://tp.media/r?marker=730427&trs=531148&p=4114&u=https%3A%2F%2Fwww.aviasales.com%2Fsearch%2FBSB1210BHZ1&campaign_id=100","updated":"2026-06-24T06:33:35.223Z"},"SAO":{"origin":"BSB","destination":"SAO","bestDeparture":"2026-10-17","bestBooking":"2026-06-24","priceBase":38,"low":30,"lowDate":"2026-05-28","dropAbs":0,"dropPct":0,"currency":"EUR","airline":"","confidence":"high","book":"https://tp.media/r?marker=730427&trs=531148&p=4114&u=https%3A%2F%2Fwww.aviasales.com%2Fsearch%2FBSB1710SAO1&campaign_id=100","updated":"2026-06-24T06:33:35.223Z"},"RIO":{"origin":"BSB","destination":"RIO","bestDeparture":"2026-10-07","bestBooking":"2026-06-24","priceBase":50,"low":37,"lowDate":"2026-06-07","dropAbs":0,"dropPct":0,"currency":"EUR","airline":"","confidence":"high","book":"https://tp.media/r?marker=730427&trs=531148&p=4114&u=https%3A%2F%2Fwww.aviasales.com%2Fsearch%2FBSB0710RIO1&campaign_id=100","updated":"2026-06-24T06:33:35.223Z"},"REC":{"origin":"BSB","destination":"REC","bestDeparture":"2026-10-28","bestBooking":"2026-06-24","priceBase":54,"low":47,"lowDate":"2026-06-09","dropAbs":0,"dropPct":0,"currency":"EUR","airline":"","confidence":"high","book":"https://tp.media/r?marker=730427&trs=531148&p=4114&u=https%3A%2F%2Fwww.aviasales.com%2Fsearch%2FBSB2810REC1&campaign_id=100","updated":"2026-06-24T06:33:35.223Z"},"GYN":{"origin":"BSB","destination":"GYN","bestDeparture":"2026-10-30","bestBooking":"2026-06-24","priceBase":54,"low":54,"lowDate":"2026-06-24","dropAbs":1,"dropPct":2,"currency":"EUR","airline":"","confidence":"high","book":"https://tp.media/r?marker=730427&trs=531148&p=4114&u=https%3A%2F%2Fwww.aviasales.com%2Fsearch%2FBSB3010GYN1&campaign_id=100","updated":"2026-06-24T06:33:35.223Z"},"VIX":{"origin":"BSB","destination":"VIX","bestDeparture":"2026-08-21","bestBooking":"2026-06-24","priceBase":63,"low":53,"lowDate":"2026-06-09","dropAbs":0,"dropPct":0,"currency":"EUR","airline":"","confidence":"high","book":"https://tp.media/r?marker=730427&trs=531148&p=4114&u=https%3A%2F%2Fwww.aviasales.com%2Fsearch%2FBSB2108VIX1&campaign_id=100","updated":"2026-06-24T06:33:35.223Z"},"SSA":{"origin":"BSB","destination":"SSA","bestDeparture":"2026-09-16","bestBooking":"2026-06-24","priceBase":67,"low":47,"lowDate":"2026-05-31","dropAbs":0,"dropPct":0,"currency":"EUR","airline":"","confidence":"high","book":"https://tp.media/r?marker=730427&trs=531148&p=4114&u=https%3A%2F%2Fwww.aviasales.com%2Fsearch%2FBSB1609SSA1&campaign_id=100","updated":"2026-06-24T06:33:35.223Z"},"CPV":{"origin":"BSB","destination":"CPV","bestDeparture":"2026-07-18","bestBooking":"2026-06-24","priceBase":78,"low":69,"lowDate":"2026-06-16","dropAbs":0,"dropPct":0,"currency":"EUR","airline":"","confidence":"high","book":"https://tp.media/r?marker=730427&trs=531148&p=4114&u=https%3A%2F%2Fwww.aviasales.com%2Fsearch%2FBSB1807CPV1&campaign_id=100","updated":"2026-06-24T06:33:35.223Z"},"MAB":{"origin":"BSB","destination":"MAB","bestDeparture":"2026-09-30","bestBooking":"2026-06-24","priceBase":78,"low":78,"lowDate":"2026-06-21","dropAbs":0,"dropPct":0,"currency":"EUR","airline":"","confidence":"high","book":"https://tp.media/r?marker=730427&trs=531148&p=4114&u=https%3A%2F%2Fwww.aviasales.com%2Fsearch%2FBSB3009MAB1&campaign_id=100","updated":"2026-06-24T06:33:35.223Z"},"JPA":{"origin":"BSB","destination":"JPA","bestDeparture":"2026-07-21","bestBooking":"2026-06-24","priceBase":87,"low":86,"lowDate":"2026-06-22","dropAbs":0,"dropPct":0,"currency":"EUR","airline":"","confidence":"high","book":"https://tp.media/r?marker=730427&trs=531148&p=4114&u=https%3A%2F%2Fwww.aviasales.com%2Fsearch%2FBSB2107JPA1&campaign_id=100","updated":"2026-06-24T06:33:35.223Z"},"FLN":{"origin":"BSB","destination":"FLN","bestDeparture":"2026-06-29","bestBooking":"2026-06-24","priceBase":90,"low":73,"lowDate":"2026-06-14","dropAbs":0,"dropPct":0,"currency":"EUR","airline":"","confidence":"high","book":"https://tp.media/r?marker=730427&trs=531148&p=4114&u=https%3A%2F%2Fwww.aviasales.com%2Fsearch%2FBSB2906FLN1&campaign_id=100","updated":"2026-06-24T06:33:35.223Z"},"CWB":{"origin":"BSB","destination":"CWB","bestDeparture":"2026-07-21","bestBooking":"2026-06-24","priceBase":93,"low":51,"lowDate":"2026-06-09","dropAbs":0,"dropPct":0,"currency":"EUR","airline":"","confidence":"high","book":"https://tp.media/r?marker=730427&trs=531148&p=4114&u=https%3A%2F%2Fwww.aviasales.com%2Fsearch%2FBSB2107CWB1&campaign_id=100","updated":"2026-06-24T06:33:35.223Z"},"CGB":{"origin":"BSB","destination":"CGB","bestDeparture":"2026-08-02","bestBooking":"2026-06-24","priceBase":96,"low":62,"lowDate":"2026-06-06","dropAbs":0,"dropPct":0,"currency":"EUR","airline":"","confidence":"high","book":"https://tp.media/r?marker=730427&trs=531148&p=4114&u=https%3A%2F%2Fwww.aviasales.com%2Fsearch%2FBSB0208CGB1&campaign_id=100","updated":"2026-06-24T06:33:35.223Z"},"PFB":{"origin":"BSB","destination":"PFB","bestDeparture":"2026-07-29","bestBooking":"2026-06-24","priceBase":98,"low":97,"lowDate":"2026-06-20","dropAbs":0,"dropPct":0,"currency":"EUR","airline":"","confidence":"high","book":"https://tp.media/r?marker=730427&trs=531148&p=4114&u=https%3A%2F%2Fwww.aviasales.com%2Fsearch%2FBSB2907PFB1&campaign_id=100","updated":"2026-06-24T06:33:35.223Z"},"IOS":{"origin":"BSB","destination":"IOS","bestDeparture":"2026-09-09","bestBooking":"2026-06-24","priceBase":101,"low":86,"lowDate":"2026-06-14","dropAbs":0,"dropPct":0,"currency":"EUR","airline":"","confidence":"high","book":"https://tp.media/r?marker=730427&trs=531148&p=4114&u=https%3A%2F%2Fwww.aviasales.com%2Fsearch%2FBSB0909IOS1&campaign_id=100","updated":"2026-06-24T06:33:35.223Z"},"PMW":{"origin":"BSB","destination":"PMW","bestDeparture":"2026-07-16","bestBooking":"2026-06-24","priceBase":107,"low":106,"lowDate":"2026-06-22","dropAbs":0,"dropPct":0,"currency":"EUR","airline":"","confidence":"high","book":"https://tp.media/r?marker=730427&trs=531148&p=4114&u=https%3A%2F%2Fwww.aviasales.com%2Fsearch%2FBSB1607PMW1&campaign_id=100","updated":"2026-06-24T06:33:35.223Z"},"THE":{"origin":"BSB","destination":"THE","bestDeparture":"2026-08-28","bestBooking":"2026-06-24","priceBase":112,"low":112,"lowDate":"2026-06-24","dropAbs":1,"dropPct":1,"currency":"EUR","airline":"","confidence":"high","book":"https://tp.media/r?marker=730427&trs=531148&p=4114&u=https%3A%2F%2Fwww.aviasales.com%2Fsearch%2FBSB2808THE1&campaign_id=100","updated":"2026-06-24T06:33:35.223Z"},"MCZ":{"origin":"BSB","destination":"MCZ","bestDeparture":"2027-01-01","bestBooking":"2026-06-24","priceBase":125,"low":125,"lowDate":"2026-06-24","dropAbs":0,"dropPct":0,"currency":"EUR","airline":"","confidence":"high","book":"https://tp.media/r?marker=730427&trs=531148&p=4114&u=https%3A%2F%2Fwww.aviasales.com%2Fsearch%2FBSB0101MCZ1&campaign_id=100","updated":"2026-06-24T06:33:35.223Z"},"IGU":{"origin":"BSB","destination":"IGU","bestDeparture":"2026-12-26","bestBooking":"2026-06-24","priceBase":132,"low":59,"lowDate":"2026-06-01","dropAbs":0,"dropPct":0,"currency":"EUR","airline":"","confidence":"high","book":"https://tp.media/r?marker=730427&trs=531148&p=4114&u=https%3A%2F%2Fwww.aviasales.com%2Fsearch%2FBSB2612IGU1&campaign_id=100","updated":"2026-06-24T06:33:35.223Z"},"TUR":{"origin":"BSB","destination":"TUR","bestDeparture":"2026-09-30","bestBooking":"2026-06-24","priceBase":138,"low":137,"lowDate":"2026-06-21","dropAbs":0,"dropPct":0,"currency":"EUR","airline":"","confidence":"high","book":"https://tp.media/r?marker=730427&trs=531148&p=4114&u=https%3A%2F%2Fwww.aviasales.com%2Fsearch%2FBSB3009TUR1&campaign_id=100","updated":"2026-06-24T06:33:35.223Z"},"BEL":{"origin":"BSB","destination":"BEL","bestDeparture":"2026-08-16","bestBooking":"2026-06-24","priceBase":141,"low":136,"lowDate":"2026-06-17","dropAbs":0,"dropPct":0,"currency":"EUR","airline":"","confidence":"high","book":"https://tp.media/r?marker=730427&trs=531148&p=4114&u=https%3A%2F%2Fwww.aviasales.com%2Fsearch%2FBSB1608BEL1&campaign_id=100","updated":"2026-06-24T06:33:35.223Z"},"FOR":{"origin":"BSB","destination":"FOR","bestDeparture":"2026-07-17","bestBooking":"2026-06-24","priceBase":145,"low":99,"lowDate":"2026-06-10","dropAbs":0,"dropPct":0,"currency":"EUR","airline":"","confidence":"high","book":"https://tp.media/r?marker=730427&trs=531148&p=4114&u=https%3A%2F%2Fwww.aviasales.com%2Fsearch%2FBSB1707FOR1&campaign_id=100","updated":"2026-06-24T06:33:35.223Z"},"SCL":{"origin":"BSB","destination":"SCL","bestDeparture":"2026-07-28","bestBooking":"2026-06-24","priceBase":145,"low":144,"lowDate":"2026-06-20","dropAbs":0,"dropPct":0,"currency":"EUR","airline":"","confidence":"high","book":"https://tp.media/r?marker=730427&trs=531148&p=4114&u=https%3A%2F%2Fwww.aviasales.com%2Fsearch%2FBSB2807SCL1&campaign_id=100","updated":"2026-06-24T06:33:35.223Z"},"SLZ":{"origin":"BSB","destination":"SLZ","bestDeparture":"2026-07-17","bestBooking":"2026-06-24","priceBase":146,"low":76,"lowDate":"2026-06-01","dropAbs":0,"dropPct":0,"currency":"EUR","airline":"","confidence":"high","book":"https://tp.media/r?marker=730427&trs=531148&p=4114&u=https%3A%2F%2Fwww.aviasales.com%2Fsearch%2FBSB1707SLZ1&campaign_id=100","updated":"2026-06-24T06:33:35.223Z"},"MAO":{"origin":"BSB","destination":"MAO","bestDeparture":"2026-07-29","bestBooking":"2026-06-24","priceBase":158,"low":157,"lowDate":"2026-06-21","dropAbs":0,"dropPct":0,"currency":"EUR","airline":"","confidence":"high","book":"https://tp.media/r?marker=730427&trs=531148&p=4114&u=https%3A%2F%2Fwww.aviasales.com%2Fsearch%2FBSB2907MAO1&campaign_id=100","updated":"2026-06-24T06:33:35.223Z"},"BUE":{"origin":"BSB","destination":"BUE","bestDeparture":"2026-08-31","bestBooking":"2026-06-24","priceBase":162,"low":160,"lowDate":"2026-06-18","dropAbs":0,"dropPct":0,"currency":"EUR","airline":"","confidence":"high","book":"https://tp.media/r?marker=730427&trs=531148&p=4114&u=https%3A%2F%2Fwww.aviasales.com%2Fsearch%2FBSB3108BUE1&campaign_id=100","updated":"2026-06-24T06:33:35.223Z"},"CZS":{"origin":"BSB","destination":"CZS","bestDeparture":"2026-08-01","bestBooking":"2026-06-24","priceBase":166,"low":165,"lowDate":"2026-06-22","dropAbs":0,"dropPct":0,"currency":"EUR","airline":"","confidence":"high","book":"https://tp.media/r?marker=730427&trs=531148&p=4114&u=https%3A%2F%2Fwww.aviasales.com%2Fsearch%2FBSB0108CZS1&campaign_id=100","updated":"2026-06-24T06:33:35.223Z"},"NAT":{"origin":"BSB","destination":"NAT","bestDeparture":"2026-07-04","bestBooking":"2026-06-24","priceBase":182,"low":86,"lowDate":"2026-05-28","dropAbs":0,"dropPct":0,"currency":"EUR","airline":"","confidence":"high","book":"https://tp.media/r?marker=730427&trs=531148&p=4114&u=https%3A%2F%2Fwww.aviasales.com%2Fsearch%2FBSB0407NAT1&campaign_id=100","updated":"2026-06-24T06:33:35.223Z"},"BOG":{"origin":"BSB","destination":"BOG","bestDeparture":"2026-07-12","bestBooking":"2026-06-24","priceBase":186,"low":185,"lowDate":"2026-06-22","dropAbs":0,"dropPct":0,"currency":"EUR","airline":"","confidence":"high","book":"https://tp.media/r?marker=730427&trs=531148&p=4114&u=https%3A%2F%2Fwww.aviasales.com%2Fsearch%2FBSB1207BOG1&campaign_id=100","updated":"2026-06-24T06:33:35.223Z"},"SMR":{"origin":"BSB","destination":"SMR","bestDeparture":"2026-07-18","bestBooking":"2026-06-24","priceBase":189,"low":187,"lowDate":"2026-06-21","dropAbs":0,"dropPct":0,"currency":"EUR","airline":"","confidence":"high","book":"https://tp.media/r?marker=730427&trs=531148&p=4114&u=https%3A%2F%2Fwww.aviasales.com%2Fsearch%2FBSB1807SMR1&campaign_id=100","updated":"2026-06-24T06:33:35.223Z"},"CTG":{"origin":"BSB","destination":"CTG","bestDeparture":"2026-07-18","bestBooking":"2026-06-24","priceBase":210,"low":208,"lowDate":"2026-06-21","dropAbs":0,"dropPct":0,"currency":"EUR","airline":"","confidence":"high","book":"https://tp.media/r?marker=730427&trs=531148&p=4114&u=https%3A%2F%2Fwww.aviasales.com%2Fsearch%2FBSB1807CTG1&campaign_id=100","updated":"2026-06-24T06:33:35.223Z"},"STM":{"origin":"BSB","destination":"STM","bestDeparture":"2026-07-26","bestBooking":"2026-06-24","priceBase":232,"low":155,"lowDate":"2026-06-23","dropAbs":0,"dropPct":0,"currency":"EUR","airline":"","confidence":"high","book":"https://tp.media/r?marker=730427&trs=531148&p=4114&u=https%3A%2F%2Fwww.aviasales.com%2Fsearch%2FBSB2607STM1&campaign_id=100","updated":"2026-06-24T06:33:35.223Z"},"PBM":{"origin":"BSB","destination":"PBM","bestDeparture":"2026-07-12","bestBooking":"2026-06-24","priceBase":233,"low":231,"lowDate":"2026-06-22","dropAbs":0,"dropPct":0,"currency":"EUR","airline":"","confidence":"high","book":"https://tp.media/r?marker=730427&trs=531148&p=4114&u=https%3A%2F%2Fwww.aviasales.com%2Fsearch%2FBSB1207PBM1&campaign_id=100","updated":"2026-06-24T06:33:35.223Z"},"LIM":{"origin":"BSB","destination":"LIM","bestDeparture":"2026-10-19","bestBooking":"2026-06-24","priceBase":239,"low":175,"lowDate":"2026-06-02","dropAbs":0,"dropPct":0,"currency":"EUR","airline":"","confidence":"high","book":"https://tp.media/r?marker=730427&trs=531148&p=4114&u=https%3A%2F%2Fwww.aviasales.com%2Fsearch%2FBSB1910LIM1&campaign_id=100","updated":"2026-06-24T06:33:35.223Z"},"ADZ":{"origin":"BSB","destination":"ADZ","bestDeparture":"2026-08-14","bestBooking":"2026-06-24","priceBase":240,"low":240,"lowDate":"2026-06-24","dropAbs":2,"dropPct":1,"currency":"EUR","airline":"","confidence":"high","book":"https://tp.media/r?marker=730427&trs=531148&p=4114&u=https%3A%2F%2Fwww.aviasales.com%2Fsearch%2FBSB1408ADZ1&campaign_id=100","updated":"2026-06-24T06:33:35.223Z"},"MIA":{"origin":"BSB","destination":"MIA","bestDeparture":"2026-08-05","bestBooking":"2026-06-24","priceBase":275,"low":275,"lowDate":"2026-06-24","dropAbs":2,"dropPct":1,"currency":"EUR","airline":"","confidence":"high","book":"https://tp.media/r?marker=730427&trs=531148&p=4114&u=https%3A%2F%2Fwww.aviasales.com%2Fsearch%2FBSB0508MIA1&campaign_id=100","updated":"2026-06-24T06:33:35.223Z"},"CUZ":{"origin":"BSB","destination":"CUZ","bestDeparture":"2026-06-27","bestBooking":"2026-06-24","priceBase":289,"low":224,"lowDate":"2026-06-14","dropAbs":0,"dropPct":0,"currency":"EUR","airline":"","confidence":"high","book":"https://tp.media/r?marker=730427&trs=531148&p=4114&u=https%3A%2F%2Fwww.aviasales.com%2Fsearch%2FBSB2706CUZ1&campaign_id=100","updated":"2026-06-24T06:33:35.223Z"},"PTY":{"origin":"BSB","destination":"PTY","bestDeparture":"2026-07-12","bestBooking":"2026-06-24","priceBase":295,"low":292,"lowDate":"2026-06-22","dropAbs":0,"dropPct":0,"currency":"EUR","airline":"","confidence":"high","book":"https://tp.media/r?marker=730427&trs=531148&p=4114&u=https%3A%2F%2Fwww.aviasales.com%2Fsearch%2FBSB1207PTY1&campaign_id=100","updated":"2026-06-24T06:33:35.223Z"},"MEX":{"origin":"BSB","destination":"MEX","bestDeparture":"2026-07-06","bestBooking":"2026-06-24","priceBase":304,"low":304,"lowDate":"2026-06-24","dropAbs":3,"dropPct":1,"currency":"EUR","airline":"","confidence":"high","book":"https://tp.media/r?marker=730427&trs=531148&p=4114&u=https%3A%2F%2Fwww.aviasales.com%2Fsearch%2FBSB0607MEX1&campaign_id=100","updated":"2026-06-24T06:33:35.223Z"},"BVB":{"origin":"BSB","destination":"BVB","bestDeparture":"2026-06-30","bestBooking":"2026-06-24","priceBase":324,"low":320,"lowDate":"2026-06-18","dropAbs":0,"dropPct":0,"currency":"EUR","airline":"","confidence":"high","book":"https://tp.media/r?marker=730427&trs=531148&p=4114&u=https%3A%2F%2Fwww.aviasales.com%2Fsearch%2FBSB3006BVB1&campaign_id=100","updated":"2026-06-24T06:33:35.223Z"},"SWF":{"origin":"BSB","destination":"SWF","bestDeparture":"2026-10-01","bestBooking":"2026-06-24","priceBase":387,"low":384,"lowDate":"2026-06-20","dropAbs":0,"dropPct":0,"currency":"EUR","airline":"","confidence":"high","book":"https://tp.media/r?marker=730427&trs=531148&p=4114&u=https%3A%2F%2Fwww.aviasales.com%2Fsearch%2FBSB0110SWF1&campaign_id=100","updated":"2026-06-24T06:33:35.223Z"},"YTO":{"origin":"BSB","destination":"YTO","bestDeparture":"2026-08-17","bestBooking":"2026-06-24","priceBase":398,"low":398,"lowDate":"2026-06-24","dropAbs":3,"dropPct":1,"currency":"EUR","airline":"","confidence":"high","book":"https://tp.media/r?marker=730427&trs=531148&p=4114&u=https%3A%2F%2Fwww.aviasales.com%2Fsearch%2FBSB1708YTO1&campaign_id=100","updated":"2026-06-24T06:33:35.223Z"},"BOS":{"origin":"BSB","destination":"BOS","bestDeparture":"2026-08-17","bestBooking":"2026-06-24","priceBase":425,"low":425,"lowDate":"2026-06-24","dropAbs":4,"dropPct":1,"currency":"EUR","airline":"","confidence":"high","book":"https://tp.media/r?marker=730427&trs=531148&p=4114&u=https%3A%2F%2Fwww.aviasales.com%2Fsearch%2FBSB1708BOS1&campaign_id=100","updated":"2026-06-24T06:33:35.223Z"},"SDQ":{"origin":"BSB","destination":"SDQ","bestDeparture":"2026-06-24","bestBooking":"2026-06-24","priceBase":426,"low":426,"lowDate":"2026-06-24","dropAbs":3,"dropPct":1,"currency":"EUR","airline":"","confidence":"high","book":"https://tp.media/r?marker=730427&trs=531148&p=4114&u=https%3A%2F%2Fwww.aviasales.com%2Fsearch%2FBSB2406SDQ1&campaign_id=100","updated":"2026-06-24T06:33:35.223Z"},"NYC":{"origin":"BSB","destination":"NYC","bestDeparture":"2026-10-01","bestBooking":"2026-06-24","priceBase":427,"low":273,"lowDate":"2026-05-28","dropAbs":0,"dropPct":0,"currency":"EUR","airline":"","confidence":"high","book":"https://tp.media/r?marker=730427&trs=531148&p=4114&u=https%3A%2F%2Fwww.aviasales.com%2Fsearch%2FBSB0110NYC1&campaign_id=100","updated":"2026-06-24T06:33:35.223Z"},"YQB":{"origin":"BSB","destination":"YQB","bestDeparture":"2026-08-17","bestBooking":"2026-06-24","priceBase":445,"low":445,"lowDate":"2026-06-24","dropAbs":4,"dropPct":1,"currency":"EUR","airline":"","confidence":"high","book":"https://tp.media/r?marker=730427&trs=531148&p=4114&u=https%3A%2F%2Fwww.aviasales.com%2Fsearch%2FBSB1708YQB1&campaign_id=100","updated":"2026-06-24T06:33:35.223Z"},"LAX":{"origin":"BSB","destination":"LAX","bestDeparture":"2026-12-25","bestBooking":"2026-06-24","priceBase":481,"low":476,"lowDate":"2026-06-20","dropAbs":0,"dropPct":0,"currency":"EUR","airline":"","confidence":"high","book":"https://tp.media/r?marker=730427&trs=531148&p=4114&u=https%3A%2F%2Fwww.aviasales.com%2Fsearch%2FBSB2512LAX1&campaign_id=100","updated":"2026-06-24T06:33:35.223Z"},"PAR":{"origin":"BSB","destination":"PAR","bestDeparture":"2026-09-15","bestBooking":"2026-06-24","priceBase":482,"low":477,"lowDate":"2026-06-20","dropAbs":0,"dropPct":0,"currency":"EUR","airline":"","confidence":"high","book":"https://tp.media/r?marker=730427&trs=531148&p=4114&u=https%3A%2F%2Fwww.aviasales.com%2Fsearch%2FBSB1509PAR1&campaign_id=100","updated":"2026-06-24T06:33:35.223Z"},"FLL":{"origin":"BSB","destination":"FLL","bestDeparture":"2026-07-05","bestBooking":"2026-06-24","priceBase":495,"low":361,"lowDate":"2026-06-17","dropAbs":0,"dropPct":0,"currency":"EUR","airline":"","confidence":"high","book":"https://tp.media/r?marker=730427&trs=531148&p=4114&u=https%3A%2F%2Fwww.aviasales.com%2Fsearch%2FBSB0507FLL1&campaign_id=100","updated":"2026-06-24T06:33:35.223Z"},"YVR":{"origin":"BSB","destination":"YVR","bestDeparture":"2026-08-22","bestBooking":"2026-06-24","priceBase":507,"low":413,"lowDate":"2026-06-10","dropAbs":0,"dropPct":0,"currency":"EUR","airline":"","confidence":"high","book":"https://tp.media/r?marker=730427&trs=531148&p=4114&u=https%3A%2F%2Fwww.aviasales.com%2Fsearch%2FBSB2208YVR1&campaign_id=100","updated":"2026-06-24T06:33:35.223Z"},"TIA":{"origin":"BSB","destination":"TIA","bestDeparture":"2026-09-30","bestBooking":"2026-06-24","priceBase":508,"low":508,"lowDate":"2026-06-24","dropAbs":4,"dropPct":1,"currency":"EUR","airline":"","confidence":"high","book":"https://tp.media/r?marker=730427&trs=531148&p=4114&u=https%3A%2F%2Fwww.aviasales.com%2Fsearch%2FBSB3009TIA1&campaign_id=100","updated":"2026-06-24T06:33:35.223Z"},"SEA":{"origin":"BSB","destination":"SEA","bestDeparture":"2026-07-10","bestBooking":"2026-06-24","priceBase":542,"low":534,"lowDate":"2026-06-18","dropAbs":0,"dropPct":0,"currency":"EUR","airline":"","confidence":"high","book":"https://tp.media/r?marker=730427&trs=531148&p=4114&u=https%3A%2F%2Fwww.aviasales.com%2Fsearch%2FBSB1007SEA1&campaign_id=100","updated":"2026-06-24T06:33:35.223Z"},"ROM":{"origin":"BSB","destination":"ROM","bestDeparture":"2026-08-20","bestBooking":"2026-06-24","priceBase":561,"low":505,"lowDate":"2026-06-10","dropAbs":0,"dropPct":0,"currency":"EUR","airline":"","confidence":"high","book":"https://tp.media/r?marker=730427&trs=531148&p=4114&u=https%3A%2F%2Fwww.aviasales.com%2Fsearch%2FBSB2008ROM1&campaign_id=100","updated":"2026-06-24T06:33:35.223Z"},"ONT":{"origin":"BSB","destination":"ONT","bestDeparture":"2026-12-25","bestBooking":"2026-06-24","priceBase":585,"low":579,"lowDate":"2026-06-20","dropAbs":0,"dropPct":0,"currency":"EUR","airline":"","confidence":"high","book":"https://tp.media/r?marker=730427&trs=531148&p=4114&u=https%3A%2F%2Fwww.aviasales.com%2Fsearch%2FBSB2512ONT1&campaign_id=100","updated":"2026-06-24T06:33:35.223Z"},"BRU":{"origin":"BSB","destination":"BRU","bestDeparture":"2026-12-15","bestBooking":"2026-06-24","priceBase":591,"low":503,"lowDate":"2026-06-14","dropAbs":0,"dropPct":0,"currency":"EUR","airline":"","confidence":"high","book":"https://tp.media/r?marker=730427&trs=531148&p=4114&u=https%3A%2F%2Fwww.aviasales.com%2Fsearch%2FBSB1512BRU1&campaign_id=100","updated":"2026-06-24T06:33:35.223Z"},"DFW":{"origin":"BSB","destination":"DFW","bestDeparture":"2026-12-22","bestBooking":"2026-06-24","priceBase":600,"low":592,"lowDate":"2026-06-17","dropAbs":0,"dropPct":0,"currency":"EUR","airline":"","confidence":"high","book":"https://tp.media/r?marker=730427&trs=531148&p=4114&u=https%3A%2F%2Fwww.aviasales.com%2Fsearch%2FBSB2212DFW1&campaign_id=100","updated":"2026-06-24T06:33:35.223Z"},"AUH":{"origin":"BSB","destination":"AUH","bestDeparture":"2026-06-28","bestBooking":"2026-06-24","priceBase":609,"low":601,"lowDate":"2026-06-18","dropAbs":0,"dropPct":0,"currency":"EUR","airline":"","confidence":"high","book":"https://tp.media/r?marker=730427&trs=531148&p=4114&u=https%3A%2F%2Fwww.aviasales.com%2Fsearch%2FBSB2806AUH1&campaign_id=100","updated":"2026-06-24T06:33:35.223Z"},"HAM":{"origin":"BSB","destination":"HAM","bestDeparture":"2026-07-31","bestBooking":"2026-06-24","priceBase":657,"low":651,"lowDate":"2026-06-20","dropAbs":0,"dropPct":0,"currency":"EUR","airline":"","confidence":"high","book":"https://tp.media/r?marker=730427&trs=531148&p=4114&u=https%3A%2F%2Fwww.aviasales.com%2Fsearch%2FBSB3107HAM1&campaign_id=100","updated":"2026-06-24T06:33:35.223Z"},"TBS":{"origin":"BSB","destination":"TBS","bestDeparture":"2026-07-05","bestBooking":"2026-06-24","priceBase":662,"low":662,"lowDate":"2026-06-24","dropAbs":5,"dropPct":1,"currency":"EUR","airline":"","confidence":"high","book":"https://tp.media/r?marker=730427&trs=531148&p=4114&u=https%3A%2F%2Fwww.aviasales.com%2Fsearch%2FBSB0507TBS1&campaign_id=100","updated":"2026-06-24T06:33:35.223Z"},"ALB":{"origin":"BSB","destination":"ALB","bestDeparture":"2026-06-27","bestBooking":"2026-06-24","priceBase":691,"low":691,"lowDate":"2026-06-24","dropAbs":6,"dropPct":1,"currency":"EUR","airline":"","confidence":"high","book":"https://tp.media/r?marker=730427&trs=531148&p=4114&u=https%3A%2F%2Fwww.aviasales.com%2Fsearch%2FBSB2706ALB1&campaign_id=100","updated":"2026-06-24T06:33:35.223Z"},"BKK":{"origin":"BSB","destination":"BKK","bestDeparture":"2026-09-15","bestBooking":"2026-06-24","priceBase":805,"low":798,"lowDate":"2026-06-20","dropAbs":0,"dropPct":0,"currency":"EUR","airline":"","confidence":"high","book":"https://tp.media/r?marker=730427&trs=531148&p=4114&u=https%3A%2F%2Fwww.aviasales.com%2Fsearch%2FBSB1509BKK1&campaign_id=100","updated":"2026-06-24T06:33:35.223Z"},"BUS":{"origin":"BSB","destination":"BUS","bestDeparture":"2026-07-04","bestBooking":"2026-06-24","priceBase":816,"low":816,"lowDate":"2026-06-24","dropAbs":7,"dropPct":1,"currency":"EUR","airline":"","confidence":"high","book":"https://tp.media/r?marker=730427&trs=531148&p=4114&u=https%3A%2F%2Fwww.aviasales.com%2Fsearch%2FBSB0407BUS1&campaign_id=100","updated":"2026-06-24T06:33:35.223Z"},"IST":{"origin":"BSB","destination":"IST","bestDeparture":"2026-06-28","bestBooking":"2026-06-24","priceBase":829,"low":829,"lowDate":"2026-06-24","dropAbs":0,"dropPct":0,"currency":"EUR","airline":"","confidence":"high","book":"https://tp.media/r?marker=730427&trs=531148&p=4114&u=https%3A%2F%2Fwww.aviasales.com%2Fsearch%2FBSB2806IST1&campaign_id=100","updated":"2026-06-24T06:33:35.223Z"},"KUT":{"origin":"BSB","destination":"KUT","bestDeparture":"2026-06-27","bestBooking":"2026-06-24","priceBase":831,"low":817,"lowDate":"2026-06-17","dropAbs":0,"dropPct":0,"currency":"EUR","airline":"","confidence":"high","book":"https://tp.media/r?marker=730427&trs=531148&p=4114&u=https%3A%2F%2Fwww.aviasales.com%2Fsearch%2FBSB2706KUT1&campaign_id=100","updated":"2026-06-24T06:33:35.223Z"},"SKG":{"origin":"BSB","destination":"SKG","bestDeparture":"2027-06-01","bestBooking":"2026-06-24","priceBase":878,"low":878,"lowDate":"2026-06-24","dropAbs":7,"dropPct":1,"currency":"EUR","airline":"","confidence":"high","book":"https://tp.media/r?marker=730427&trs=531148&p=4114&u=https%3A%2F%2Fwww.aviasales.com%2Fsearch%2FBSB0106SKG1&campaign_id=100","updated":"2026-06-24T06:33:35.223Z"},"MOW":{"origin":"BSB","destination":"MOW","bestDeparture":"2026-08-03","bestBooking":"2026-06-24","priceBase":881,"low":735,"lowDate":"2026-06-06","dropAbs":0,"dropPct":0,"currency":"EUR","airline":"","confidence":"high","book":"https://tp.media/r?marker=730427&trs=531148&p=4114&u=https%3A%2F%2Fwww.aviasales.com%2Fsearch%2FBSB0308MOW1&campaign_id=100","updated":"2026-06-24T06:33:35.223Z"},"GOI":{"origin":"BSB","destination":"GOI","bestDeparture":"2026-08-04","bestBooking":"2026-06-24","priceBase":894,"low":886,"lowDate":"2026-06-22","dropAbs":0,"dropPct":0,"currency":"EUR","airline":"","confidence":"high","book":"https://tp.media/r?marker=730427&trs=531148&p=4114&u=https%3A%2F%2Fwww.aviasales.com%2Fsearch%2FBSB0408GOI1&campaign_id=100","updated":"2026-06-24T06:33:35.223Z"},"DEL":{"origin":"BSB","destination":"DEL","bestDeparture":"2026-07-23","bestBooking":"2026-06-24","priceBase":894,"low":894,"lowDate":"2026-06-24","dropAbs":7,"dropPct":1,"currency":"EUR","airline":"","confidence":"high","book":"https://tp.media/r?marker=730427&trs=531148&p=4114&u=https%3A%2F%2Fwww.aviasales.com%2Fsearch%2FBSB2307DEL1&campaign_id=100","updated":"2026-06-24T06:33:35.223Z"},"BAK":{"origin":"BSB","destination":"BAK","bestDeparture":"2026-06-30","bestBooking":"2026-06-24","priceBase":910,"low":902,"lowDate":"2026-06-22","dropAbs":0,"dropPct":0,"currency":"EUR","airline":"","confidence":"high","book":"https://tp.media/r?marker=730427&trs=531148&p=4114&u=https%3A%2F%2Fwww.aviasales.com%2Fsearch%2FBSB3006BAK1&campaign_id=100","updated":"2026-06-24T06:33:35.223Z"},"NGO":{"origin":"BSB","destination":"NGO","bestDeparture":"2026-07-16","bestBooking":"2026-06-24","priceBase":1066,"low":1057,"lowDate":"2026-06-22","dropAbs":0,"dropPct":0,"currency":"EUR","airline":"","confidence":"high","book":"https://tp.media/r?marker=730427&trs=531148&p=4114&u=https%3A%2F%2Fwww.aviasales.com%2Fsearch%2FBSB1607NGO1&campaign_id=100","updated":"2026-06-24T06:33:35.223Z"},"TAS":{"origin":"BSB","destination":"TAS","bestDeparture":"2026-06-25","bestBooking":"2026-06-24","priceBase":1076,"low":1066,"lowDate":"2026-06-20","dropAbs":0,"dropPct":0,"currency":"EUR","airline":"","confidence":"high","book":"https://tp.media/r?marker=730427&trs=531148&p=4114&u=https%3A%2F%2Fwww.aviasales.com%2Fsearch%2FBSB2506TAS1&campaign_id=100","updated":"2026-06-24T06:33:35.223Z"},"DPS":{"origin":"BSB","destination":"DPS","bestDeparture":"2026-06-27","bestBooking":"2026-06-24","priceBase":1442,"low":1442,"lowDate":"2026-06-24","dropAbs":12,"dropPct":1,"currency":"EUR","airline":"","confidence":"high","book":"https://tp.media/r?marker=730427&trs=531148&p=4114&u=https%3A%2F%2Fwww.aviasales.com%2Fsearch%2FBSB2706DPS1&campaign_id=100","updated":"2026-06-24T06:33:35.223Z"}}}