{"origin":"TRN","generated":"2026-07-21T05:41:32.858Z","count":141,"routes":{"TIA":{"origin":"TRN","destination":"TIA","bestDeparture":"2026-09-16","bestBooking":"2026-07-21","priceBase":11,"low":11,"lowDate":"2026-07-21","dropAbs":1,"dropPct":8,"currency":"EUR","airline":"","confidence":"high","book":"https://tp.media/r?marker=730427&trs=531148&p=4114&u=https%3A%2F%2Fwww.aviasales.com%2Fsearch%2FTRN1609TIA1&campaign_id=100","updated":"2026-07-21T05:41:32.858Z"},"PMO":{"origin":"TRN","destination":"PMO","bestDeparture":"2026-08-19","bestBooking":"2026-07-21","priceBase":16,"low":13,"lowDate":"2026-06-01","dropAbs":0,"dropPct":0,"currency":"EUR","airline":"","confidence":"high","book":"https://tp.media/r?marker=730427&trs=531148&p=4114&u=https%3A%2F%2Fwww.aviasales.com%2Fsearch%2FTRN1908PMO1&campaign_id=100","updated":"2026-07-21T05:41:32.858Z"},"BCN":{"origin":"TRN","destination":"BCN","bestDeparture":"2026-09-14","bestBooking":"2026-07-21","priceBase":16,"low":14,"lowDate":"2026-06-06","dropAbs":0,"dropPct":0,"currency":"EUR","airline":"","confidence":"high","book":"https://tp.media/r?marker=730427&trs=531148&p=4114&u=https%3A%2F%2Fwww.aviasales.com%2Fsearch%2FTRN1409BCN1&campaign_id=100","updated":"2026-07-21T05:41:32.858Z"},"SUF":{"origin":"TRN","destination":"SUF","bestDeparture":"2026-08-24","bestBooking":"2026-07-21","priceBase":17,"low":17,"lowDate":"2026-07-18","dropAbs":0,"dropPct":0,"currency":"EUR","airline":"","confidence":"high","book":"https://tp.media/r?marker=730427&trs=531148&p=4114&u=https%3A%2F%2Fwww.aviasales.com%2Fsearch%2FTRN2408SUF1&campaign_id=100","updated":"2026-07-21T05:41:32.858Z"},"ROM":{"origin":"TRN","destination":"ROM","bestDeparture":"2026-10-29","bestBooking":"2026-07-21","priceBase":18,"low":18,"lowDate":"2026-06-21","dropAbs":0,"dropPct":0,"currency":"EUR","airline":"","confidence":"high","book":"https://tp.media/r?marker=730427&trs=531148&p=4114&u=https%3A%2F%2Fwww.aviasales.com%2Fsearch%2FTRN2910ROM1&campaign_id=100","updated":"2026-07-21T05:41:32.858Z"},"BUD":{"origin":"TRN","destination":"BUD","bestDeparture":"2026-08-21","bestBooking":"2026-07-21","priceBase":18,"low":13,"lowDate":"2026-06-01","dropAbs":0,"dropPct":0,"currency":"EUR","airline":"","confidence":"high","book":"https://tp.media/r?marker=730427&trs=531148&p=4114&u=https%3A%2F%2Fwww.aviasales.com%2Fsearch%2FTRN2108BUD1&campaign_id=100","updated":"2026-07-21T05:41:32.858Z"},"CTA":{"origin":"TRN","destination":"CTA","bestDeparture":"2026-08-19","bestBooking":"2026-07-21","priceBase":18,"low":16,"lowDate":"2026-07-06","dropAbs":0,"dropPct":0,"currency":"EUR","airline":"","confidence":"high","book":"https://tp.media/r?marker=730427&trs=531148&p=4114&u=https%3A%2F%2Fwww.aviasales.com%2Fsearch%2FTRN1908CTA1&campaign_id=100","updated":"2026-07-21T05:41:32.858Z"},"RMO":{"origin":"TRN","destination":"RMO","bestDeparture":"2026-10-07","bestBooking":"2026-07-21","priceBase":20,"low":16,"lowDate":"2026-07-17","dropAbs":0,"dropPct":0,"currency":"EUR","airline":"","confidence":"high","book":"https://tp.media/r?marker=730427&trs=531148&p=4114&u=https%3A%2F%2Fwww.aviasales.com%2Fsearch%2FTRN0710RMO1&campaign_id=100","updated":"2026-07-21T05:41:32.858Z"},"MAD":{"origin":"TRN","destination":"MAD","bestDeparture":"2026-09-09","bestBooking":"2026-07-21","priceBase":21,"low":20,"lowDate":"2026-07-16","dropAbs":0,"dropPct":0,"currency":"EUR","airline":"","confidence":"high","book":"https://tp.media/r?marker=730427&trs=531148&p=4114&u=https%3A%2F%2Fwww.aviasales.com%2Fsearch%2FTRN0909MAD1&campaign_id=100","updated":"2026-07-21T05:41:32.858Z"},"CPH":{"origin":"TRN","destination":"CPH","bestDeparture":"2026-09-09","bestBooking":"2026-07-21","priceBase":21,"low":19,"lowDate":"2026-06-10","dropAbs":0,"dropPct":0,"currency":"EUR","airline":"","confidence":"high","book":"https://tp.media/r?marker=730427&trs=531148&p=4114&u=https%3A%2F%2Fwww.aviasales.com%2Fsearch%2FTRN0909CPH1&campaign_id=100","updated":"2026-07-21T05:41:32.858Z"},"AHO":{"origin":"TRN","destination":"AHO","bestDeparture":"2026-09-07","bestBooking":"2026-07-21","priceBase":23,"low":23,"lowDate":"2026-07-18","dropAbs":0,"dropPct":0,"currency":"EUR","airline":"","confidence":"high","book":"https://tp.media/r?marker=730427&trs=531148&p=4114&u=https%3A%2F%2Fwww.aviasales.com%2Fsearch%2FTRN0709AHO1&campaign_id=100","updated":"2026-07-21T05:41:32.858Z"},"BRU":{"origin":"TRN","destination":"BRU","bestDeparture":"2026-09-04","bestBooking":"2026-07-21","priceBase":26,"low":16,"lowDate":"2026-05-26","dropAbs":0,"dropPct":0,"currency":"EUR","airline":"","confidence":"high","book":"https://tp.media/r?marker=730427&trs=531148&p=4114&u=https%3A%2F%2Fwww.aviasales.com%2Fsearch%2FTRN0409BRU1&campaign_id=100","updated":"2026-07-21T05:41:32.858Z"},"RAK":{"origin":"TRN","destination":"RAK","bestDeparture":"2026-09-22","bestBooking":"2026-07-21","priceBase":27,"low":27,"lowDate":"2026-07-21","dropAbs":6,"dropPct":18,"currency":"EUR","airline":"","confidence":"high","book":"https://tp.media/r?marker=730427&trs=531148&p=4114&u=https%3A%2F%2Fwww.aviasales.com%2Fsearch%2FTRN2209RAK1&campaign_id=100","updated":"2026-07-21T05:41:32.858Z"},"OLB":{"origin":"TRN","destination":"OLB","bestDeparture":"2026-08-18","bestBooking":"2026-07-21","priceBase":30,"low":28,"lowDate":"2026-07-06","dropAbs":0,"dropPct":0,"currency":"EUR","airline":"","confidence":"high","book":"https://tp.media/r?marker=730427&trs=531148&p=4114&u=https%3A%2F%2Fwww.aviasales.com%2Fsearch%2FTRN1808OLB1&campaign_id=100","updated":"2026-07-21T05:41:32.858Z"},"CAG":{"origin":"TRN","destination":"CAG","bestDeparture":"2026-08-22","bestBooking":"2026-07-21","priceBase":31,"low":17,"lowDate":"2026-05-26","dropAbs":0,"dropPct":0,"currency":"EUR","airline":"","confidence":"high","book":"https://tp.media/r?marker=730427&trs=531148&p=4114&u=https%3A%2F%2Fwww.aviasales.com%2Fsearch%2FTRN2208CAG1&campaign_id=100","updated":"2026-07-21T05:41:32.858Z"},"VLC":{"origin":"TRN","destination":"VLC","bestDeparture":"2026-10-01","bestBooking":"2026-07-21","priceBase":32,"low":20,"lowDate":"2026-07-10","dropAbs":0,"dropPct":0,"currency":"EUR","airline":"","confidence":"high","book":"https://tp.media/r?marker=730427&trs=531148&p=4114&u=https%3A%2F%2Fwww.aviasales.com%2Fsearch%2FTRN0110VLC1&campaign_id=100","updated":"2026-07-21T05:41:32.858Z"},"MIL":{"origin":"TRN","destination":"MIL","bestDeparture":"2026-09-14","bestBooking":"2026-07-21","priceBase":32,"low":30,"lowDate":"2026-06-14","dropAbs":0,"dropPct":0,"currency":"EUR","airline":"","confidence":"high","book":"https://tp.media/r?marker=730427&trs=531148&p=4114&u=https%3A%2F%2Fwww.aviasales.com%2Fsearch%2FTRN1409MIL1&campaign_id=100","updated":"2026-07-21T05:41:32.858Z"},"SOF":{"origin":"TRN","destination":"SOF","bestDeparture":"2026-08-19","bestBooking":"2026-07-21","priceBase":34,"low":16,"lowDate":"2026-06-18","dropAbs":0,"dropPct":0,"currency":"EUR","airline":"","confidence":"high","book":"https://tp.media/r?marker=730427&trs=531148&p=4114&u=https%3A%2F%2Fwww.aviasales.com%2Fsearch%2FTRN1908SOF1&campaign_id=100","updated":"2026-07-21T05:41:32.858Z"},"BRI":{"origin":"TRN","destination":"BRI","bestDeparture":"2026-12-01","bestBooking":"2026-07-21","priceBase":41,"low":18,"lowDate":"2026-05-26","dropAbs":0,"dropPct":0,"currency":"EUR","airline":"","confidence":"high","book":"https://tp.media/r?marker=730427&trs=531148&p=4114&u=https%3A%2F%2Fwww.aviasales.com%2Fsearch%2FTRN0112BRI1&campaign_id=100","updated":"2026-07-21T05:41:32.858Z"},"PMI":{"origin":"TRN","destination":"PMI","bestDeparture":"2026-09-25","bestBooking":"2026-07-21","priceBase":43,"low":43,"lowDate":"2026-07-19","dropAbs":0,"dropPct":0,"currency":"EUR","airline":"","confidence":"high","book":"https://tp.media/r?marker=730427&trs=531148&p=4114&u=https%3A%2F%2Fwww.aviasales.com%2Fsearch%2FTRN2509PMI1&campaign_id=100","updated":"2026-07-21T05:41:32.858Z"},"FOG":{"origin":"TRN","destination":"FOG","bestDeparture":"2026-10-23","bestBooking":"2026-07-21","priceBase":46,"low":46,"lowDate":"2026-07-21","dropAbs":0,"dropPct":0,"currency":"EUR","airline":"","confidence":"high","book":"https://tp.media/r?marker=730427&trs=531148&p=4114&u=https%3A%2F%2Fwww.aviasales.com%2Fsearch%2FTRN2310FOG1&campaign_id=100","updated":"2026-07-21T05:41:32.858Z"},"PAR":{"origin":"TRN","destination":"PAR","bestDeparture":"2026-11-12","bestBooking":"2026-07-21","priceBase":46,"low":32,"lowDate":"2026-05-31","dropAbs":0,"dropPct":0,"currency":"EUR","airline":"","confidence":"high","book":"https://tp.media/r?marker=730427&trs=531148&p=4114&u=https%3A%2F%2Fwww.aviasales.com%2Fsearch%2FTRN1211PAR1&campaign_id=100","updated":"2026-07-21T05:41:32.858Z"},"ALG":{"origin":"TRN","destination":"ALG","bestDeparture":"2026-10-01","bestBooking":"2026-07-21","priceBase":48,"low":48,"lowDate":"2026-07-17","dropAbs":0,"dropPct":0,"currency":"EUR","airline":"","confidence":"high","book":"https://tp.media/r?marker=730427&trs=531148&p=4114&u=https%3A%2F%2Fwww.aviasales.com%2Fsearch%2FTRN0110ALG1&campaign_id=100","updated":"2026-07-21T05:41:32.858Z"},"IAS":{"origin":"TRN","destination":"IAS","bestDeparture":"2026-09-15","bestBooking":"2026-07-21","priceBase":49,"low":30,"lowDate":"2026-06-12","dropAbs":0,"dropPct":0,"currency":"EUR","airline":"","confidence":"high","book":"https://tp.media/r?marker=730427&trs=531148&p=4114&u=https%3A%2F%2Fwww.aviasales.com%2Fsearch%2FTRN1509IAS1&campaign_id=100","updated":"2026-07-21T05:41:32.858Z"},"WAW":{"origin":"TRN","destination":"WAW","bestDeparture":"2026-09-16","bestBooking":"2026-07-21","priceBase":50,"low":23,"lowDate":"2026-06-17","dropAbs":0,"dropPct":0,"currency":"EUR","airline":"","confidence":"high","book":"https://tp.media/r?marker=730427&trs=531148&p=4114&u=https%3A%2F%2Fwww.aviasales.com%2Fsearch%2FTRN1609WAW1&campaign_id=100","updated":"2026-07-21T05:41:32.858Z"},"TLL":{"origin":"TRN","destination":"TLL","bestDeparture":"2026-09-16","bestBooking":"2026-07-21","priceBase":53,"low":53,"lowDate":"2026-07-21","dropAbs":38,"dropPct":42,"currency":"EUR","airline":"","confidence":"high","book":"https://tp.media/r?marker=730427&trs=531148&p=4114&u=https%3A%2F%2Fwww.aviasales.com%2Fsearch%2FTRN1609TLL1&campaign_id=100","updated":"2026-07-21T05:41:32.858Z"},"NAP":{"origin":"TRN","destination":"NAP","bestDeparture":"2026-08-18","bestBooking":"2026-07-21","priceBase":54,"low":17,"lowDate":"2026-06-14","dropAbs":0,"dropPct":0,"currency":"EUR","airline":"","confidence":"high","book":"https://tp.media/r?marker=730427&trs=531148&p=4114&u=https%3A%2F%2Fwww.aviasales.com%2Fsearch%2FTRN1808NAP1&campaign_id=100","updated":"2026-07-21T05:41:32.858Z"},"LON":{"origin":"TRN","destination":"LON","bestDeparture":"2026-08-07","bestBooking":"2026-07-21","priceBase":55,"low":14,"lowDate":"2026-05-28","dropAbs":0,"dropPct":0,"currency":"EUR","airline":"","confidence":"high","book":"https://tp.media/r?marker=730427&trs=531148&p=4114&u=https%3A%2F%2Fwww.aviasales.com%2Fsearch%2FTRN0708LON1&campaign_id=100","updated":"2026-07-21T05:41:32.858Z"},"GDN":{"origin":"TRN","destination":"GDN","bestDeparture":"2026-09-09","bestBooking":"2026-07-21","priceBase":55,"low":55,"lowDate":"2026-07-16","dropAbs":0,"dropPct":0,"currency":"EUR","airline":"","confidence":"high","book":"https://tp.media/r?marker=730427&trs=531148&p=4114&u=https%3A%2F%2Fwww.aviasales.com%2Fsearch%2FTRN0909GDN1&campaign_id=100","updated":"2026-07-21T05:41:32.858Z"},"KRK":{"origin":"TRN","destination":"KRK","bestDeparture":"2026-09-04","bestBooking":"2026-07-21","priceBase":56,"low":13,"lowDate":"2026-06-22","dropAbs":0,"dropPct":0,"currency":"EUR","airline":"","confidence":"high","book":"https://tp.media/r?marker=730427&trs=531148&p=4114&u=https%3A%2F%2Fwww.aviasales.com%2Fsearch%2FTRN0409KRK1&campaign_id=100","updated":"2026-07-21T05:41:32.858Z"},"VCE":{"origin":"TRN","destination":"VCE","bestDeparture":"2026-08-29","bestBooking":"2026-07-21","priceBase":59,"low":36,"lowDate":"2026-06-20","dropAbs":0,"dropPct":0,"currency":"EUR","airline":"","confidence":"high","book":"https://tp.media/r?marker=730427&trs=531148&p=4114&u=https%3A%2F%2Fwww.aviasales.com%2Fsearch%2FTRN2908VCE1&campaign_id=100","updated":"2026-07-21T05:41:32.858Z"},"BJA":{"origin":"TRN","destination":"BJA","bestDeparture":"2026-10-01","bestBooking":"2026-07-21","priceBase":59,"low":59,"lowDate":"2026-07-17","dropAbs":0,"dropPct":0,"currency":"EUR","airline":"","confidence":"high","book":"https://tp.media/r?marker=730427&trs=531148&p=4114&u=https%3A%2F%2Fwww.aviasales.com%2Fsearch%2FTRN0110BJA1&campaign_id=100","updated":"2026-07-21T05:41:32.858Z"},"VNO":{"origin":"TRN","destination":"VNO","bestDeparture":"2026-09-02","bestBooking":"2026-07-21","priceBase":60,"low":24,"lowDate":"2026-06-10","dropAbs":0,"dropPct":0,"currency":"EUR","airline":"","confidence":"high","book":"https://tp.media/r?marker=730427&trs=531148&p=4114&u=https%3A%2F%2Fwww.aviasales.com%2Fsearch%2FTRN0209VNO1&campaign_id=100","updated":"2026-07-21T05:41:32.858Z"},"CRV":{"origin":"TRN","destination":"CRV","bestDeparture":"2026-09-14","bestBooking":"2026-07-21","priceBase":61,"low":61,"lowDate":"2026-07-17","dropAbs":0,"dropPct":0,"currency":"EUR","airline":"","confidence":"high","book":"https://tp.media/r?marker=730427&trs=531148&p=4114&u=https%3A%2F%2Fwww.aviasales.com%2Fsearch%2FTRN1409CRV1&campaign_id=100","updated":"2026-07-21T05:41:32.858Z"},"CGN":{"origin":"TRN","destination":"CGN","bestDeparture":"2026-10-08","bestBooking":"2026-07-21","priceBase":62,"low":61,"lowDate":"2026-07-16","dropAbs":0,"dropPct":0,"currency":"EUR","airline":"","confidence":"high","book":"https://tp.media/r?marker=730427&trs=531148&p=4114&u=https%3A%2F%2Fwww.aviasales.com%2Fsearch%2FTRN0810CGN1&campaign_id=100","updated":"2026-07-21T05:41:32.858Z"},"NCE":{"origin":"TRN","destination":"NCE","bestDeparture":"2027-03-01","bestBooking":"2026-07-21","priceBase":62,"low":58,"lowDate":"2026-06-30","dropAbs":0,"dropPct":0,"currency":"EUR","airline":"","confidence":"high","book":"https://tp.media/r?marker=730427&trs=531148&p=4114&u=https%3A%2F%2Fwww.aviasales.com%2Fsearch%2FTRN0103NCE1&campaign_id=100","updated":"2026-07-21T05:41:32.858Z"},"ESU":{"origin":"TRN","destination":"ESU","bestDeparture":"2026-08-20","bestBooking":"2026-07-21","priceBase":64,"low":64,"lowDate":"2026-07-18","dropAbs":0,"dropPct":0,"currency":"EUR","airline":"","confidence":"high","book":"https://tp.media/r?marker=730427&trs=531148&p=4114&u=https%3A%2F%2Fwww.aviasales.com%2Fsearch%2FTRN2008ESU1&campaign_id=100","updated":"2026-07-21T05:41:32.858Z"},"EVN":{"origin":"TRN","destination":"EVN","bestDeparture":"2026-09-27","bestBooking":"2026-07-21","priceBase":67,"low":59,"lowDate":"2026-05-28","dropAbs":0,"dropPct":0,"currency":"EUR","airline":"","confidence":"high","book":"https://tp.media/r?marker=730427&trs=531148&p=4114&u=https%3A%2F%2Fwww.aviasales.com%2Fsearch%2FTRN2709EVN1&campaign_id=100","updated":"2026-07-21T05:41:32.858Z"},"PSA":{"origin":"TRN","destination":"PSA","bestDeparture":"2026-07-29","bestBooking":"2026-07-21","priceBase":68,"low":68,"lowDate":"2026-07-20","dropAbs":0,"dropPct":0,"currency":"EUR","airline":"","confidence":"high","book":"https://tp.media/r?marker=730427&trs=531148&p=4114&u=https%3A%2F%2Fwww.aviasales.com%2Fsearch%2FTRN2907PSA1&campaign_id=100","updated":"2026-07-21T05:41:32.858Z"},"IST":{"origin":"TRN","destination":"IST","bestDeparture":"2026-09-14","bestBooking":"2026-07-21","priceBase":68,"low":65,"lowDate":"2026-07-12","dropAbs":0,"dropPct":0,"currency":"EUR","airline":"","confidence":"high","book":"https://tp.media/r?marker=730427&trs=531148&p=4114&u=https%3A%2F%2Fwww.aviasales.com%2Fsearch%2FTRN1409IST1&campaign_id=100","updated":"2026-07-21T05:41:32.858Z"},"FAO":{"origin":"TRN","destination":"FAO","bestDeparture":"2026-09-26","bestBooking":"2026-07-21","priceBase":68,"low":68,"lowDate":"2026-07-18","dropAbs":0,"dropPct":0,"currency":"EUR","airline":"","confidence":"high","book":"https://tp.media/r?marker=730427&trs=531148&p=4114&u=https%3A%2F%2Fwww.aviasales.com%2Fsearch%2FTRN2609FAO1&campaign_id=100","updated":"2026-07-21T05:41:32.858Z"},"VRN":{"origin":"TRN","destination":"VRN","bestDeparture":"2026-07-23","bestBooking":"2026-07-21","priceBase":68,"low":61,"lowDate":"2026-07-10","dropAbs":0,"dropPct":0,"currency":"EUR","airline":"","confidence":"high","book":"https://tp.media/r?marker=730427&trs=531148&p=4114&u=https%3A%2F%2Fwww.aviasales.com%2Fsearch%2FTRN2307VRN1&campaign_id=100","updated":"2026-07-21T05:41:32.858Z"},"AYT":{"origin":"TRN","destination":"AYT","bestDeparture":"2026-08-28","bestBooking":"2026-07-21","priceBase":71,"low":66,"lowDate":"2026-05-28","dropAbs":0,"dropPct":0,"currency":"EUR","airline":"","confidence":"high","book":"https://tp.media/r?marker=730427&trs=531148&p=4114&u=https%3A%2F%2Fwww.aviasales.com%2Fsearch%2FTRN2808AYT1&campaign_id=100","updated":"2026-07-21T05:41:32.858Z"},"BLQ":{"origin":"TRN","destination":"BLQ","bestDeparture":"2026-07-21","bestBooking":"2026-07-21","priceBase":72,"low":48,"lowDate":"2026-07-04","dropAbs":0,"dropPct":0,"currency":"EUR","airline":"","confidence":"high","book":"https://tp.media/r?marker=730427&trs=531148&p=4114&u=https%3A%2F%2Fwww.aviasales.com%2Fsearch%2FTRN2107BLQ1&campaign_id=100","updated":"2026-07-21T05:41:32.858Z"},"OPO":{"origin":"TRN","destination":"OPO","bestDeparture":"2026-09-09","bestBooking":"2026-07-21","priceBase":76,"low":29,"lowDate":"2026-07-14","dropAbs":0,"dropPct":0,"currency":"EUR","airline":"","confidence":"high","book":"https://tp.media/r?marker=730427&trs=531148&p=4114&u=https%3A%2F%2Fwww.aviasales.com%2Fsearch%2FTRN0909OPO1&campaign_id=100","updated":"2026-07-21T05:41:32.858Z"},"BUH":{"origin":"TRN","destination":"BUH","bestDeparture":"2026-08-03","bestBooking":"2026-07-21","priceBase":77,"low":18,"lowDate":"2026-07-06","dropAbs":0,"dropPct":0,"currency":"EUR","airline":"","confidence":"high","book":"https://tp.media/r?marker=730427&trs=531148&p=4114&u=https%3A%2F%2Fwww.aviasales.com%2Fsearch%2FTRN0308BUH1&campaign_id=100","updated":"2026-07-21T05:41:32.858Z"},"AGP":{"origin":"TRN","destination":"AGP","bestDeparture":"2026-08-11","bestBooking":"2026-07-21","priceBase":80,"low":33,"lowDate":"2026-07-08","dropAbs":0,"dropPct":0,"currency":"EUR","airline":"","confidence":"high","book":"https://tp.media/r?marker=730427&trs=531148&p=4114&u=https%3A%2F%2Fwww.aviasales.com%2Fsearch%2FTRN1108AGP1&campaign_id=100","updated":"2026-07-21T05:41:32.858Z"},"CMN":{"origin":"TRN","destination":"CMN","bestDeparture":"2026-09-21","bestBooking":"2026-07-21","priceBase":81,"low":81,"lowDate":"2026-07-21","dropAbs":2,"dropPct":2,"currency":"EUR","airline":"","confidence":"high","book":"https://tp.media/r?marker=730427&trs=531148&p=4114&u=https%3A%2F%2Fwww.aviasales.com%2Fsearch%2FTRN2109CMN1&campaign_id=100","updated":"2026-07-21T05:41:32.858Z"},"BTS":{"origin":"TRN","destination":"BTS","bestDeparture":"2026-08-30","bestBooking":"2026-07-21","priceBase":82,"low":82,"lowDate":"2026-07-21","dropAbs":29,"dropPct":26,"currency":"EUR","airline":"","confidence":"high","book":"https://tp.media/r?marker=730427&trs=531148&p=4114&u=https%3A%2F%2Fwww.aviasales.com%2Fsearch%2FTRN3008BTS1&campaign_id=100","updated":"2026-07-21T05:41:32.858Z"},"PMF":{"origin":"TRN","destination":"PMF","bestDeparture":"2026-09-09","bestBooking":"2026-07-21","priceBase":85,"low":83,"lowDate":"2026-07-08","dropAbs":0,"dropPct":0,"currency":"EUR","airline":"","confidence":"high","book":"https://tp.media/r?marker=730427&trs=531148&p=4114&u=https%3A%2F%2Fwww.aviasales.com%2Fsearch%2FTRN0909PMF1&campaign_id=100","updated":"2026-07-21T05:41:32.858Z"},"TCI":{"origin":"TRN","destination":"TCI","bestDeparture":"2026-08-28","bestBooking":"2026-07-21","priceBase":85,"low":85,"lowDate":"2026-07-20","dropAbs":0,"dropPct":0,"currency":"EUR","airline":"","confidence":"high","book":"https://tp.media/r?marker=730427&trs=531148&p=4114&u=https%3A%2F%2Fwww.aviasales.com%2Fsearch%2FTRN2808TCI1&campaign_id=100","updated":"2026-07-21T05:41:32.858Z"},"DUS":{"origin":"TRN","destination":"DUS","bestDeparture":"2026-10-27","bestBooking":"2026-07-21","priceBase":86,"low":71,"lowDate":"2026-07-10","dropAbs":0,"dropPct":0,"currency":"EUR","airline":"","confidence":"high","book":"https://tp.media/r?marker=730427&trs=531148&p=4114&u=https%3A%2F%2Fwww.aviasales.com%2Fsearch%2FTRN2710DUS1&campaign_id=100","updated":"2026-07-21T05:41:32.858Z"},"STR":{"origin":"TRN","destination":"STR","bestDeparture":"2026-07-29","bestBooking":"2026-07-21","priceBase":86,"low":58,"lowDate":"2026-07-13","dropAbs":0,"dropPct":0,"currency":"EUR","airline":"","confidence":"high","book":"https://tp.media/r?marker=730427&trs=531148&p=4114&u=https%3A%2F%2Fwww.aviasales.com%2Fsearch%2FTRN2907STR1&campaign_id=100","updated":"2026-07-21T05:41:32.858Z"},"BDS":{"origin":"TRN","destination":"BDS","bestDeparture":"2026-08-06","bestBooking":"2026-07-21","priceBase":88,"low":21,"lowDate":"2026-06-30","dropAbs":0,"dropPct":0,"currency":"EUR","airline":"","confidence":"high","book":"https://tp.media/r?marker=730427&trs=531148&p=4114&u=https%3A%2F%2Fwww.aviasales.com%2Fsearch%2FTRN0608BDS1&campaign_id=100","updated":"2026-07-21T05:41:32.858Z"},"MUC":{"origin":"TRN","destination":"MUC","bestDeparture":"2026-09-21","bestBooking":"2026-07-21","priceBase":89,"low":65,"lowDate":"2026-06-29","dropAbs":0,"dropPct":0,"currency":"EUR","airline":"","confidence":"high","book":"https://tp.media/r?marker=730427&trs=531148&p=4114&u=https%3A%2F%2Fwww.aviasales.com%2Fsearch%2FTRN2109MUC1&campaign_id=100","updated":"2026-07-21T05:41:32.858Z"},"RBA":{"origin":"TRN","destination":"RBA","bestDeparture":"2026-08-18","bestBooking":"2026-07-21","priceBase":94,"low":94,"lowDate":"2026-07-18","dropAbs":0,"dropPct":0,"currency":"EUR","airline":"","confidence":"high","book":"https://tp.media/r?marker=730427&trs=531148&p=4114&u=https%3A%2F%2Fwww.aviasales.com%2Fsearch%2FTRN1808RBA1&campaign_id=100","updated":"2026-07-21T05:41:32.858Z"},"BER":{"origin":"TRN","destination":"BER","bestDeparture":"2026-08-05","bestBooking":"2026-07-21","priceBase":94,"low":58,"lowDate":"2026-05-28","dropAbs":0,"dropPct":0,"currency":"EUR","airline":"","confidence":"high","book":"https://tp.media/r?marker=730427&trs=531148&p=4114&u=https%3A%2F%2Fwww.aviasales.com%2Fsearch%2FTRN0508BER1&campaign_id=100","updated":"2026-07-21T05:41:32.858Z"},"CLJ":{"origin":"TRN","destination":"CLJ","bestDeparture":"2026-08-06","bestBooking":"2026-07-21","priceBase":95,"low":95,"lowDate":"2026-07-16","dropAbs":0,"dropPct":0,"currency":"EUR","airline":"","confidence":"high","book":"https://tp.media/r?marker=730427&trs=531148&p=4114&u=https%3A%2F%2Fwww.aviasales.com%2Fsearch%2FTRN0608CLJ1&campaign_id=100","updated":"2026-07-21T05:41:32.858Z"},"HEL":{"origin":"TRN","destination":"HEL","bestDeparture":"2026-10-24","bestBooking":"2026-07-21","priceBase":96,"low":96,"lowDate":"2026-07-02","dropAbs":0,"dropPct":0,"currency":"EUR","airline":"","confidence":"high","book":"https://tp.media/r?marker=730427&trs=531148&p=4114&u=https%3A%2F%2Fwww.aviasales.com%2Fsearch%2FTRN2410HEL1&campaign_id=100","updated":"2026-07-21T05:41:32.858Z"},"HER":{"origin":"TRN","destination":"HER","bestDeparture":"2026-10-01","bestBooking":"2026-07-21","priceBase":97,"low":97,"lowDate":"2026-07-16","dropAbs":0,"dropPct":0,"currency":"EUR","airline":"","confidence":"high","book":"https://tp.media/r?marker=730427&trs=531148&p=4114&u=https%3A%2F%2Fwww.aviasales.com%2Fsearch%2FTRN0110HER1&campaign_id=100","updated":"2026-07-21T05:41:32.858Z"},"ZRH":{"origin":"TRN","destination":"ZRH","bestDeparture":"2026-09-03","bestBooking":"2026-07-21","priceBase":98,"low":98,"lowDate":"2026-07-17","dropAbs":0,"dropPct":0,"currency":"EUR","airline":"","confidence":"high","book":"https://tp.media/r?marker=730427&trs=531148&p=4114&u=https%3A%2F%2Fwww.aviasales.com%2Fsearch%2FTRN0309ZRH1&campaign_id=100","updated":"2026-07-21T05:41:32.858Z"},"KTW":{"origin":"TRN","destination":"KTW","bestDeparture":"2026-08-11","bestBooking":"2026-07-21","priceBase":99,"low":99,"lowDate":"2026-07-20","dropAbs":0,"dropPct":0,"currency":"EUR","airline":"","confidence":"high","book":"https://tp.media/r?marker=730427&trs=531148&p=4114&u=https%3A%2F%2Fwww.aviasales.com%2Fsearch%2FTRN1108KTW1&campaign_id=100","updated":"2026-07-21T05:41:32.858Z"},"CFU":{"origin":"TRN","destination":"CFU","bestDeparture":"2026-07-22","bestBooking":"2026-07-21","priceBase":99,"low":90,"lowDate":"2026-07-12","dropAbs":0,"dropPct":0,"currency":"EUR","airline":"","confidence":"high","book":"https://tp.media/r?marker=730427&trs=531148&p=4114&u=https%3A%2F%2Fwww.aviasales.com%2Fsearch%2FTRN2207CFU1&campaign_id=100","updated":"2026-07-21T05:41:32.858Z"},"TBS":{"origin":"TRN","destination":"TBS","bestDeparture":"2026-09-27","bestBooking":"2026-07-21","priceBase":107,"low":107,"lowDate":"2026-07-21","dropAbs":31,"dropPct":22,"currency":"EUR","airline":"","confidence":"high","book":"https://tp.media/r?marker=730427&trs=531148&p=4114&u=https%3A%2F%2Fwww.aviasales.com%2Fsearch%2FTRN2709TBS1&campaign_id=100","updated":"2026-07-21T05:41:32.858Z"},"RZE":{"origin":"TRN","destination":"RZE","bestDeparture":"2026-08-12","bestBooking":"2026-07-21","priceBase":109,"low":109,"lowDate":"2026-07-21","dropAbs":0,"dropPct":0,"currency":"EUR","airline":"","confidence":"high","book":"https://tp.media/r?marker=730427&trs=531148&p=4114&u=https%3A%2F%2Fwww.aviasales.com%2Fsearch%2FTRN1208RZE1&campaign_id=100","updated":"2026-07-21T05:41:32.858Z"},"AMS":{"origin":"TRN","destination":"AMS","bestDeparture":"2026-08-01","bestBooking":"2026-07-21","priceBase":112,"low":51,"lowDate":"2026-05-31","dropAbs":0,"dropPct":0,"currency":"EUR","airline":"","confidence":"high","book":"https://tp.media/r?marker=730427&trs=531148&p=4114&u=https%3A%2F%2Fwww.aviasales.com%2Fsearch%2FTRN0108AMS1&campaign_id=100","updated":"2026-07-21T05:41:32.858Z"},"TLS":{"origin":"TRN","destination":"TLS","bestDeparture":"2026-07-21","bestBooking":"2026-07-21","priceBase":120,"low":119,"lowDate":"2026-07-18","dropAbs":0,"dropPct":0,"currency":"EUR","airline":"","confidence":"high","book":"https://tp.media/r?marker=730427&trs=531148&p=4114&u=https%3A%2F%2Fwww.aviasales.com%2Fsearch%2FTRN2107TLS1&campaign_id=100","updated":"2026-07-21T05:41:32.858Z"},"VIE":{"origin":"TRN","destination":"VIE","bestDeparture":"2026-07-22","bestBooking":"2026-07-21","priceBase":120,"low":78,"lowDate":"2026-07-08","dropAbs":0,"dropPct":0,"currency":"EUR","airline":"","confidence":"high","book":"https://tp.media/r?marker=730427&trs=531148&p=4114&u=https%3A%2F%2Fwww.aviasales.com%2Fsearch%2FTRN2207VIE1&campaign_id=100","updated":"2026-07-21T05:41:32.858Z"},"ZAG":{"origin":"TRN","destination":"ZAG","bestDeparture":"2026-08-14","bestBooking":"2026-07-21","priceBase":123,"low":109,"lowDate":"2026-07-18","dropAbs":0,"dropPct":0,"currency":"EUR","airline":"","confidence":"high","book":"https://tp.media/r?marker=730427&trs=531148&p=4114&u=https%3A%2F%2Fwww.aviasales.com%2Fsearch%2FTRN1408ZAG1&campaign_id=100","updated":"2026-07-21T05:41:32.858Z"},"GVA":{"origin":"TRN","destination":"GVA","bestDeparture":"2026-08-13","bestBooking":"2026-07-21","priceBase":124,"low":124,"lowDate":"2026-07-16","dropAbs":0,"dropPct":0,"currency":"EUR","airline":"","confidence":"high","book":"https://tp.media/r?marker=730427&trs=531148&p=4114&u=https%3A%2F%2Fwww.aviasales.com%2Fsearch%2FTRN1308GVA1&campaign_id=100","updated":"2026-07-21T05:41:32.858Z"},"ATH":{"origin":"TRN","destination":"ATH","bestDeparture":"2026-08-07","bestBooking":"2026-07-21","priceBase":126,"low":36,"lowDate":"2026-07-02","dropAbs":0,"dropPct":0,"currency":"EUR","airline":"","confidence":"high","book":"https://tp.media/r?marker=730427&trs=531148&p=4114&u=https%3A%2F%2Fwww.aviasales.com%2Fsearch%2FTRN0708ATH1&campaign_id=100","updated":"2026-07-21T05:41:32.858Z"},"FLR":{"origin":"TRN","destination":"FLR","bestDeparture":"2026-07-23","bestBooking":"2026-07-21","priceBase":128,"low":51,"lowDate":"2026-07-10","dropAbs":0,"dropPct":0,"currency":"EUR","airline":"","confidence":"high","book":"https://tp.media/r?marker=730427&trs=531148&p=4114&u=https%3A%2F%2Fwww.aviasales.com%2Fsearch%2FTRN2307FLR1&campaign_id=100","updated":"2026-07-21T05:41:32.858Z"},"REG":{"origin":"TRN","destination":"REG","bestDeparture":"2026-07-25","bestBooking":"2026-07-21","priceBase":129,"low":108,"lowDate":"2026-07-10","dropAbs":0,"dropPct":0,"currency":"EUR","airline":"","confidence":"high","book":"https://tp.media/r?marker=730427&trs=531148&p=4114&u=https%3A%2F%2Fwww.aviasales.com%2Fsearch%2FTRN2507REG1&campaign_id=100","updated":"2026-07-21T05:41:32.858Z"},"BEG":{"origin":"TRN","destination":"BEG","bestDeparture":"2026-08-03","bestBooking":"2026-07-21","priceBase":133,"low":71,"lowDate":"2026-06-30","dropAbs":0,"dropPct":0,"currency":"EUR","airline":"","confidence":"high","book":"https://tp.media/r?marker=730427&trs=531148&p=4114&u=https%3A%2F%2Fwww.aviasales.com%2Fsearch%2FTRN0308BEG1&campaign_id=100","updated":"2026-07-21T05:41:32.858Z"},"SVQ":{"origin":"TRN","destination":"SVQ","bestDeparture":"2026-07-22","bestBooking":"2026-07-21","priceBase":133,"low":133,"lowDate":"2026-07-21","dropAbs":0,"dropPct":0,"currency":"EUR","airline":"","confidence":"high","book":"https://tp.media/r?marker=730427&trs=531148&p=4114&u=https%3A%2F%2Fwww.aviasales.com%2Fsearch%2FTRN2207SVQ1&campaign_id=100","updated":"2026-07-21T05:41:32.858Z"},"KUT":{"origin":"TRN","destination":"KUT","bestDeparture":"2026-08-12","bestBooking":"2026-07-21","priceBase":133,"low":133,"lowDate":"2026-07-19","dropAbs":0,"dropPct":0,"currency":"EUR","airline":"","confidence":"high","book":"https://tp.media/r?marker=730427&trs=531148&p=4114&u=https%3A%2F%2Fwww.aviasales.com%2Fsearch%2FTRN1208KUT1&campaign_id=100","updated":"2026-07-21T05:41:32.858Z"},"LIS":{"origin":"TRN","destination":"LIS","bestDeparture":"2026-07-22","bestBooking":"2026-07-21","priceBase":142,"low":135,"lowDate":"2026-07-13","dropAbs":0,"dropPct":0,"currency":"EUR","airline":"","confidence":"high","book":"https://tp.media/r?marker=730427&trs=531148&p=4114&u=https%3A%2F%2Fwww.aviasales.com%2Fsearch%2FTRN2207LIS1&campaign_id=100","updated":"2026-07-21T05:41:32.858Z"},"SKG":{"origin":"TRN","destination":"SKG","bestDeparture":"2026-08-06","bestBooking":"2026-07-21","priceBase":153,"low":153,"lowDate":"2026-07-21","dropAbs":0,"dropPct":0,"currency":"EUR","airline":"","confidence":"high","book":"https://tp.media/r?marker=730427&trs=531148&p=4114&u=https%3A%2F%2Fwww.aviasales.com%2Fsearch%2FTRN0608SKG1&campaign_id=100","updated":"2026-07-21T05:41:32.858Z"},"IEG":{"origin":"TRN","destination":"IEG","bestDeparture":"2026-07-28","bestBooking":"2026-07-21","priceBase":154,"low":154,"lowDate":"2026-07-19","dropAbs":0,"dropPct":0,"currency":"EUR","airline":"","confidence":"high","book":"https://tp.media/r?marker=730427&trs=531148&p=4114&u=https%3A%2F%2Fwww.aviasales.com%2Fsearch%2FTRN2807IEG1&campaign_id=100","updated":"2026-07-21T05:41:32.858Z"},"DTM":{"origin":"TRN","destination":"DTM","bestDeparture":"2026-08-10","bestBooking":"2026-07-21","priceBase":158,"low":158,"lowDate":"2026-07-21","dropAbs":0,"dropPct":0,"currency":"EUR","airline":"","confidence":"high","book":"https://tp.media/r?marker=730427&trs=531148&p=4114&u=https%3A%2F%2Fwww.aviasales.com%2Fsearch%2FTRN1008DTM1&campaign_id=100","updated":"2026-07-21T05:41:32.858Z"},"BAK":{"origin":"TRN","destination":"BAK","bestDeparture":"2026-09-27","bestBooking":"2026-07-21","priceBase":160,"low":128,"lowDate":"2026-07-02","dropAbs":0,"dropPct":0,"currency":"EUR","airline":"","confidence":"high","book":"https://tp.media/r?marker=730427&trs=531148&p=4114&u=https%3A%2F%2Fwww.aviasales.com%2Fsearch%2FTRN2709BAK1&campaign_id=100","updated":"2026-07-21T05:41:32.858Z"},"PFO":{"origin":"TRN","destination":"PFO","bestDeparture":"2026-08-03","bestBooking":"2026-07-21","priceBase":162,"low":81,"lowDate":"2026-06-30","dropAbs":0,"dropPct":0,"currency":"EUR","airline":"","confidence":"high","book":"https://tp.media/r?marker=730427&trs=531148&p=4114&u=https%3A%2F%2Fwww.aviasales.com%2Fsearch%2FTRN0308PFO1&campaign_id=100","updated":"2026-07-21T05:41:32.858Z"},"PRG":{"origin":"TRN","destination":"PRG","bestDeparture":"2026-08-08","bestBooking":"2026-07-21","priceBase":164,"low":42,"lowDate":"2026-07-13","dropAbs":0,"dropPct":0,"currency":"EUR","airline":"","confidence":"high","book":"https://tp.media/r?marker=730427&trs=531148&p=4114&u=https%3A%2F%2Fwww.aviasales.com%2Fsearch%2FTRN0808PRG1&campaign_id=100","updated":"2026-07-21T05:41:32.858Z"},"GZP":{"origin":"TRN","destination":"GZP","bestDeparture":"2026-08-18","bestBooking":"2026-07-21","priceBase":165,"low":129,"lowDate":"2026-07-14","dropAbs":0,"dropPct":0,"currency":"EUR","airline":"","confidence":"high","book":"https://tp.media/r?marker=730427&trs=531148&p=4114&u=https%3A%2F%2Fwww.aviasales.com%2Fsearch%2FTRN1808GZP1&campaign_id=100","updated":"2026-07-21T05:41:32.858Z"},"LED":{"origin":"TRN","destination":"LED","bestDeparture":"2026-09-11","bestBooking":"2026-07-21","priceBase":172,"low":172,"lowDate":"2026-07-20","dropAbs":0,"dropPct":0,"currency":"EUR","airline":"","confidence":"high","book":"https://tp.media/r?marker=730427&trs=531148&p=4114&u=https%3A%2F%2Fwww.aviasales.com%2Fsearch%2FTRN1109LED1&campaign_id=100","updated":"2026-07-21T05:41:32.858Z"},"CRA":{"origin":"TRN","destination":"CRA","bestDeparture":"2026-07-25","bestBooking":"2026-07-21","priceBase":175,"low":175,"lowDate":"2026-07-21","dropAbs":0,"dropPct":0,"currency":"EUR","airline":"","confidence":"high","book":"https://tp.media/r?marker=730427&trs=531148&p=4114&u=https%3A%2F%2Fwww.aviasales.com%2Fsearch%2FTRN2507CRA1&campaign_id=100","updated":"2026-07-21T05:41:32.858Z"},"MPL":{"origin":"TRN","destination":"MPL","bestDeparture":"2026-07-21","bestBooking":"2026-07-21","priceBase":176,"low":176,"lowDate":"2026-07-20","dropAbs":0,"dropPct":0,"currency":"EUR","airline":"","confidence":"high","book":"https://tp.media/r?marker=730427&trs=531148&p=4114&u=https%3A%2F%2Fwww.aviasales.com%2Fsearch%2FTRN2107MPL1&campaign_id=100","updated":"2026-07-21T05:41:32.858Z"},"HAJ":{"origin":"TRN","destination":"HAJ","bestDeparture":"2026-08-14","bestBooking":"2026-07-21","priceBase":177,"low":131,"lowDate":"2026-07-13","dropAbs":0,"dropPct":0,"currency":"EUR","airline":"","confidence":"high","book":"https://tp.media/r?marker=730427&trs=531148&p=4114&u=https%3A%2F%2Fwww.aviasales.com%2Fsearch%2FTRN1408HAJ1&campaign_id=100","updated":"2026-07-21T05:41:32.858Z"},"ALA":{"origin":"TRN","destination":"ALA","bestDeparture":"2026-10-02","bestBooking":"2026-07-21","priceBase":184,"low":184,"lowDate":"2026-07-21","dropAbs":6,"dropPct":3,"currency":"EUR","airline":"","confidence":"high","book":"https://tp.media/r?marker=730427&trs=531148&p=4114&u=https%3A%2F%2Fwww.aviasales.com%2Fsearch%2FTRN0210ALA1&campaign_id=100","updated":"2026-07-21T05:41:32.858Z"},"RIX":{"origin":"TRN","destination":"RIX","bestDeparture":"2026-08-07","bestBooking":"2026-07-21","priceBase":193,"low":136,"lowDate":"2026-07-09","dropAbs":0,"dropPct":0,"currency":"EUR","airline":"","confidence":"high","book":"https://tp.media/r?marker=730427&trs=531148&p=4114&u=https%3A%2F%2Fwww.aviasales.com%2Fsearch%2FTRN0708RIX1&campaign_id=100","updated":"2026-07-21T05:41:32.858Z"},"GOT":{"origin":"TRN","destination":"GOT","bestDeparture":"2026-07-28","bestBooking":"2026-07-21","priceBase":195,"low":195,"lowDate":"2026-07-21","dropAbs":0,"dropPct":0,"currency":"EUR","airline":"","confidence":"high","book":"https://tp.media/r?marker=730427&trs=531148&p=4114&u=https%3A%2F%2Fwww.aviasales.com%2Fsearch%2FTRN2807GOT1&campaign_id=100","updated":"2026-07-21T05:41:32.858Z"},"SSH":{"origin":"TRN","destination":"SSH","bestDeparture":"2026-07-30","bestBooking":"2026-07-21","priceBase":196,"low":196,"lowDate":"2026-07-18","dropAbs":0,"dropPct":0,"currency":"EUR","airline":"","confidence":"high","book":"https://tp.media/r?marker=730427&trs=531148&p=4114&u=https%3A%2F%2Fwww.aviasales.com%2Fsearch%2FTRN3007SSH1&campaign_id=100","updated":"2026-07-21T05:41:32.858Z"},"SCV":{"origin":"TRN","destination":"SCV","bestDeparture":"2026-07-27","bestBooking":"2026-07-21","priceBase":198,"low":64,"lowDate":"2026-07-13","dropAbs":0,"dropPct":0,"currency":"EUR","airline":"","confidence":"high","book":"https://tp.media/r?marker=730427&trs=531148&p=4114&u=https%3A%2F%2Fwww.aviasales.com%2Fsearch%2FTRN2707SCV1&campaign_id=100","updated":"2026-07-21T05:41:32.858Z"},"VAN":{"origin":"TRN","destination":"VAN","bestDeparture":"2026-07-31","bestBooking":"2026-07-21","priceBase":199,"low":198,"lowDate":"2026-07-16","dropAbs":0,"dropPct":0,"currency":"EUR","airline":"","confidence":"high","book":"https://tp.media/r?marker=730427&trs=531148&p=4114&u=https%3A%2F%2Fwww.aviasales.com%2Fsearch%2FTRN3107VAN1&campaign_id=100","updated":"2026-07-21T05:41:32.858Z"},"BOJ":{"origin":"TRN","destination":"BOJ","bestDeparture":"2026-07-25","bestBooking":"2026-07-21","priceBase":201,"low":68,"lowDate":"2026-07-13","dropAbs":0,"dropPct":0,"currency":"EUR","airline":"","confidence":"high","book":"https://tp.media/r?marker=730427&trs=531148&p=4114&u=https%3A%2F%2Fwww.aviasales.com%2Fsearch%2FTRN2507BOJ1&campaign_id=100","updated":"2026-07-21T05:41:32.858Z"},"KUN":{"origin":"TRN","destination":"KUN","bestDeparture":"2026-08-09","bestBooking":"2026-07-21","priceBase":201,"low":86,"lowDate":"2026-07-10","dropAbs":0,"dropPct":0,"currency":"EUR","airline":"","confidence":"high","book":"https://tp.media/r?marker=730427&trs=531148&p=4114&u=https%3A%2F%2Fwww.aviasales.com%2Fsearch%2FTRN0908KUN1&campaign_id=100","updated":"2026-07-21T05:41:32.858Z"},"TSR":{"origin":"TRN","destination":"TSR","bestDeparture":"2026-08-02","bestBooking":"2026-07-21","priceBase":204,"low":203,"lowDate":"2026-07-18","dropAbs":0,"dropPct":0,"currency":"EUR","airline":"","confidence":"high","book":"https://tp.media/r?marker=730427&trs=531148&p=4114&u=https%3A%2F%2Fwww.aviasales.com%2Fsearch%2FTRN0208TSR1&campaign_id=100","updated":"2026-07-21T05:41:32.858Z"},"ALY":{"origin":"TRN","destination":"ALY","bestDeparture":"2026-07-30","bestBooking":"2026-07-21","priceBase":204,"low":204,"lowDate":"2026-07-18","dropAbs":0,"dropPct":0,"currency":"EUR","airline":"","confidence":"high","book":"https://tp.media/r?marker=730427&trs=531148&p=4114&u=https%3A%2F%2Fwww.aviasales.com%2Fsearch%2FTRN3007ALY1&campaign_id=100","updated":"2026-07-21T05:41:32.858Z"},"STO":{"origin":"TRN","destination":"STO","bestDeparture":"2026-07-31","bestBooking":"2026-07-21","priceBase":205,"low":102,"lowDate":"2026-07-10","dropAbs":0,"dropPct":0,"currency":"EUR","airline":"","confidence":"high","book":"https://tp.media/r?marker=730427&trs=531148&p=4114&u=https%3A%2F%2Fwww.aviasales.com%2Fsearch%2FTRN3107STO1&campaign_id=100","updated":"2026-07-21T05:41:32.858Z"},"SVG":{"origin":"TRN","destination":"SVG","bestDeparture":"2026-08-14","bestBooking":"2026-07-21","priceBase":206,"low":206,"lowDate":"2026-07-21","dropAbs":0,"dropPct":0,"currency":"EUR","airline":"","confidence":"high","book":"https://tp.media/r?marker=730427&trs=531148&p=4114&u=https%3A%2F%2Fwww.aviasales.com%2Fsearch%2FTRN1408SVG1&campaign_id=100","updated":"2026-07-21T05:41:32.858Z"},"CAI":{"origin":"TRN","destination":"CAI","bestDeparture":"2026-08-06","bestBooking":"2026-07-21","priceBase":214,"low":144,"lowDate":"2026-07-14","dropAbs":0,"dropPct":0,"currency":"EUR","airline":"","confidence":"high","book":"https://tp.media/r?marker=730427&trs=531148&p=4114&u=https%3A%2F%2Fwww.aviasales.com%2Fsearch%2FTRN0608CAI1&campaign_id=100","updated":"2026-07-21T05:41:32.858Z"},"MOW":{"origin":"TRN","destination":"MOW","bestDeparture":"2026-09-05","bestBooking":"2026-07-21","priceBase":215,"low":163,"lowDate":"2026-06-02","dropAbs":0,"dropPct":0,"currency":"EUR","airline":"","confidence":"high","book":"https://tp.media/r?marker=730427&trs=531148&p=4114&u=https%3A%2F%2Fwww.aviasales.com%2Fsearch%2FTRN0509MOW1&campaign_id=100","updated":"2026-07-21T05:41:32.858Z"},"KRR":{"origin":"TRN","destination":"KRR","bestDeparture":"2026-08-27","bestBooking":"2026-07-21","priceBase":216,"low":216,"lowDate":"2026-07-18","dropAbs":0,"dropPct":0,"currency":"EUR","airline":"","confidence":"high","book":"https://tp.media/r?marker=730427&trs=531148&p=4114&u=https%3A%2F%2Fwww.aviasales.com%2Fsearch%2FTRN2708KRR1&campaign_id=100","updated":"2026-07-21T05:41:32.858Z"},"BGO":{"origin":"TRN","destination":"BGO","bestDeparture":"2026-08-01","bestBooking":"2026-07-21","priceBase":221,"low":221,"lowDate":"2026-07-20","dropAbs":0,"dropPct":0,"currency":"EUR","airline":"","confidence":"high","book":"https://tp.media/r?marker=730427&trs=531148&p=4114&u=https%3A%2F%2Fwww.aviasales.com%2Fsearch%2FTRN0108BGO1&campaign_id=100","updated":"2026-07-21T05:41:32.858Z"},"AER":{"origin":"TRN","destination":"AER","bestDeparture":"2026-07-22","bestBooking":"2026-07-21","priceBase":235,"low":235,"lowDate":"2026-07-16","dropAbs":0,"dropPct":0,"currency":"EUR","airline":"","confidence":"high","book":"https://tp.media/r?marker=730427&trs=531148&p=4114&u=https%3A%2F%2Fwww.aviasales.com%2Fsearch%2FTRN2207AER1&campaign_id=100","updated":"2026-07-21T05:41:32.858Z"},"TAS":{"origin":"TRN","destination":"TAS","bestDeparture":"2026-08-28","bestBooking":"2026-07-21","priceBase":243,"low":192,"lowDate":"2026-06-30","dropAbs":0,"dropPct":0,"currency":"EUR","airline":"","confidence":"high","book":"https://tp.media/r?marker=730427&trs=531148&p=4114&u=https%3A%2F%2Fwww.aviasales.com%2Fsearch%2FTRN2808TAS1&campaign_id=100","updated":"2026-07-21T05:41:32.858Z"},"LCA":{"origin":"TRN","destination":"LCA","bestDeparture":"2026-07-25","bestBooking":"2026-07-21","priceBase":251,"low":85,"lowDate":"2026-06-20","dropAbs":0,"dropPct":0,"currency":"EUR","airline":"","confidence":"high","book":"https://tp.media/r?marker=730427&trs=531148&p=4114&u=https%3A%2F%2Fwww.aviasales.com%2Fsearch%2FTRN2507LCA1&campaign_id=100","updated":"2026-07-21T05:41:32.858Z"},"NQZ":{"origin":"TRN","destination":"NQZ","bestDeparture":"2026-09-23","bestBooking":"2026-07-21","priceBase":251,"low":198,"lowDate":"2026-05-28","dropAbs":0,"dropPct":0,"currency":"EUR","airline":"","confidence":"high","book":"https://tp.media/r?marker=730427&trs=531148&p=4114&u=https%3A%2F%2Fwww.aviasales.com%2Fsearch%2FTRN2309NQZ1&campaign_id=100","updated":"2026-07-21T05:41:32.858Z"},"AXD":{"origin":"TRN","destination":"AXD","bestDeparture":"2026-07-21","bestBooking":"2026-07-21","priceBase":273,"low":273,"lowDate":"2026-07-20","dropAbs":0,"dropPct":0,"currency":"EUR","airline":"","confidence":"high","book":"https://tp.media/r?marker=730427&trs=531148&p=4114&u=https%3A%2F%2Fwww.aviasales.com%2Fsearch%2FTRN2107AXD1&campaign_id=100","updated":"2026-07-21T05:41:32.858Z"},"AVN":{"origin":"TRN","destination":"AVN","bestDeparture":"2026-09-23","bestBooking":"2026-07-21","priceBase":283,"low":283,"lowDate":"2026-07-19","dropAbs":0,"dropPct":0,"currency":"EUR","airline":"","confidence":"high","book":"https://tp.media/r?marker=730427&trs=531148&p=4114&u=https%3A%2F%2Fwww.aviasales.com%2Fsearch%2FTRN2309AVN1&campaign_id=100","updated":"2026-07-21T05:41:32.858Z"},"CEK":{"origin":"TRN","destination":"CEK","bestDeparture":"2026-09-27","bestBooking":"2026-07-21","priceBase":285,"low":285,"lowDate":"2026-07-21","dropAbs":0,"dropPct":0,"currency":"EUR","airline":"","confidence":"high","book":"https://tp.media/r?marker=730427&trs=531148&p=4114&u=https%3A%2F%2Fwww.aviasales.com%2Fsearch%2FTRN2709CEK1&campaign_id=100","updated":"2026-07-21T05:41:32.858Z"},"DOH":{"origin":"TRN","destination":"DOH","bestDeparture":"2026-08-02","bestBooking":"2026-07-21","priceBase":300,"low":299,"lowDate":"2026-07-18","dropAbs":0,"dropPct":0,"currency":"EUR","airline":"","confidence":"high","book":"https://tp.media/r?marker=730427&trs=531148&p=4114&u=https%3A%2F%2Fwww.aviasales.com%2Fsearch%2FTRN0208DOH1&campaign_id=100","updated":"2026-07-21T05:41:32.858Z"},"DXB":{"origin":"TRN","destination":"DXB","bestDeparture":"2026-07-23","bestBooking":"2026-07-21","priceBase":306,"low":306,"lowDate":"2026-07-21","dropAbs":0,"dropPct":0,"currency":"EUR","airline":"","confidence":"high","book":"https://tp.media/r?marker=730427&trs=531148&p=4114&u=https%3A%2F%2Fwww.aviasales.com%2Fsearch%2FTRN2307DXB1&campaign_id=100","updated":"2026-07-21T05:41:32.858Z"},"SHJ":{"origin":"TRN","destination":"SHJ","bestDeparture":"2026-07-23","bestBooking":"2026-07-21","priceBase":306,"low":306,"lowDate":"2026-07-21","dropAbs":0,"dropPct":0,"currency":"EUR","airline":"","confidence":"high","book":"https://tp.media/r?marker=730427&trs=531148&p=4114&u=https%3A%2F%2Fwww.aviasales.com%2Fsearch%2FTRN2307SHJ1&campaign_id=100","updated":"2026-07-21T05:41:32.858Z"},"SVX":{"origin":"TRN","destination":"SVX","bestDeparture":"2026-09-27","bestBooking":"2026-07-21","priceBase":312,"low":273,"lowDate":"2026-07-10","dropAbs":0,"dropPct":0,"currency":"EUR","airline":"","confidence":"high","book":"https://tp.media/r?marker=730427&trs=531148&p=4114&u=https%3A%2F%2Fwww.aviasales.com%2Fsearch%2FTRN2709SVX1&campaign_id=100","updated":"2026-07-21T05:41:32.858Z"},"BZO":{"origin":"TRN","destination":"BZO","bestDeparture":"2026-07-25","bestBooking":"2026-07-21","priceBase":328,"low":327,"lowDate":"2026-07-19","dropAbs":0,"dropPct":0,"currency":"EUR","airline":"","confidence":"high","book":"https://tp.media/r?marker=730427&trs=531148&p=4114&u=https%3A%2F%2Fwww.aviasales.com%2Fsearch%2FTRN2507BZO1&campaign_id=100","updated":"2026-07-21T05:41:32.858Z"},"KGD":{"origin":"TRN","destination":"KGD","bestDeparture":"2026-10-01","bestBooking":"2026-07-21","priceBase":332,"low":331,"lowDate":"2026-07-18","dropAbs":0,"dropPct":0,"currency":"EUR","airline":"","confidence":"high","book":"https://tp.media/r?marker=730427&trs=531148&p=4114&u=https%3A%2F%2Fwww.aviasales.com%2Fsearch%2FTRN0110KGD1&campaign_id=100","updated":"2026-07-21T05:41:32.858Z"},"VOG":{"origin":"TRN","destination":"VOG","bestDeparture":"2026-08-13","bestBooking":"2026-07-21","priceBase":368,"low":367,"lowDate":"2026-07-18","dropAbs":0,"dropPct":0,"currency":"EUR","airline":"","confidence":"high","book":"https://tp.media/r?marker=730427&trs=531148&p=4114&u=https%3A%2F%2Fwww.aviasales.com%2Fsearch%2FTRN1308VOG1&campaign_id=100","updated":"2026-07-21T05:41:32.858Z"},"NOZ":{"origin":"TRN","destination":"NOZ","bestDeparture":"2026-09-07","bestBooking":"2026-07-21","priceBase":372,"low":371,"lowDate":"2026-07-19","dropAbs":0,"dropPct":0,"currency":"EUR","airline":"","confidence":"high","book":"https://tp.media/r?marker=730427&trs=531148&p=4114&u=https%3A%2F%2Fwww.aviasales.com%2Fsearch%2FTRN0709NOZ1&campaign_id=100","updated":"2026-07-21T05:41:32.858Z"},"GUW":{"origin":"TRN","destination":"GUW","bestDeparture":"2026-08-01","bestBooking":"2026-07-21","priceBase":376,"low":360,"lowDate":"2026-07-20","dropAbs":0,"dropPct":0,"currency":"EUR","airline":"","confidence":"high","book":"https://tp.media/r?marker=730427&trs=531148&p=4114&u=https%3A%2F%2Fwww.aviasales.com%2Fsearch%2FTRN0108GUW1&campaign_id=100","updated":"2026-07-21T05:41:32.858Z"},"RIO":{"origin":"TRN","destination":"RIO","bestDeparture":"2026-09-10","bestBooking":"2026-07-21","priceBase":377,"low":377,"lowDate":"2026-07-21","dropAbs":33,"dropPct":8,"currency":"EUR","airline":"","confidence":"high","book":"https://tp.media/r?marker=730427&trs=531148&p=4114&u=https%3A%2F%2Fwww.aviasales.com%2Fsearch%2FTRN1009RIO1&campaign_id=100","updated":"2026-07-21T05:41:32.858Z"},"TJM":{"origin":"TRN","destination":"TJM","bestDeparture":"2026-07-28","bestBooking":"2026-07-21","priceBase":378,"low":317,"lowDate":"2026-07-13","dropAbs":0,"dropPct":0,"currency":"EUR","airline":"","confidence":"high","book":"https://tp.media/r?marker=730427&trs=531148&p=4114&u=https%3A%2F%2Fwww.aviasales.com%2Fsearch%2FTRN2807TJM1&campaign_id=100","updated":"2026-07-21T05:41:32.858Z"},"OUA":{"origin":"TRN","destination":"OUA","bestDeparture":"2026-11-20","bestBooking":"2026-07-21","priceBase":380,"low":379,"lowDate":"2026-07-19","dropAbs":0,"dropPct":0,"currency":"EUR","airline":"","confidence":"high","book":"https://tp.media/r?marker=730427&trs=531148&p=4114&u=https%3A%2F%2Fwww.aviasales.com%2Fsearch%2FTRN2011OUA1&campaign_id=100","updated":"2026-07-21T05:41:32.858Z"},"BSZ":{"origin":"TRN","destination":"BSZ","bestDeparture":"2026-07-27","bestBooking":"2026-07-21","priceBase":381,"low":205,"lowDate":"2026-07-02","dropAbs":0,"dropPct":0,"currency":"EUR","airline":"","confidence":"high","book":"https://tp.media/r?marker=730427&trs=531148&p=4114&u=https%3A%2F%2Fwww.aviasales.com%2Fsearch%2FTRN2707BSZ1&campaign_id=100","updated":"2026-07-21T05:41:32.858Z"},"OMS":{"origin":"TRN","destination":"OMS","bestDeparture":"2026-07-29","bestBooking":"2026-07-21","priceBase":393,"low":393,"lowDate":"2026-07-20","dropAbs":0,"dropPct":0,"currency":"EUR","airline":"","confidence":"high","book":"https://tp.media/r?marker=730427&trs=531148&p=4114&u=https%3A%2F%2Fwww.aviasales.com%2Fsearch%2FTRN2907OMS1&campaign_id=100","updated":"2026-07-21T05:41:32.858Z"},"KUF":{"origin":"TRN","destination":"KUF","bestDeparture":"2026-07-26","bestBooking":"2026-07-21","priceBase":394,"low":355,"lowDate":"2026-07-02","dropAbs":0,"dropPct":0,"currency":"EUR","airline":"","confidence":"high","book":"https://tp.media/r?marker=730427&trs=531148&p=4114&u=https%3A%2F%2Fwww.aviasales.com%2Fsearch%2FTRN2607KUF1&campaign_id=100","updated":"2026-07-21T05:41:32.858Z"},"OVB":{"origin":"TRN","destination":"OVB","bestDeparture":"2026-07-28","bestBooking":"2026-07-21","priceBase":399,"low":329,"lowDate":"2026-07-14","dropAbs":0,"dropPct":0,"currency":"EUR","airline":"","confidence":"high","book":"https://tp.media/r?marker=730427&trs=531148&p=4114&u=https%3A%2F%2Fwww.aviasales.com%2Fsearch%2FTRN2807OVB1&campaign_id=100","updated":"2026-07-21T05:41:32.858Z"},"SIN":{"origin":"TRN","destination":"SIN","bestDeparture":"2026-09-10","bestBooking":"2026-07-21","priceBase":410,"low":409,"lowDate":"2026-07-16","dropAbs":0,"dropPct":0,"currency":"EUR","airline":"","confidence":"high","book":"https://tp.media/r?marker=730427&trs=531148&p=4114&u=https%3A%2F%2Fwww.aviasales.com%2Fsearch%2FTRN1009SIN1&campaign_id=100","updated":"2026-07-21T05:41:32.858Z"},"KZN":{"origin":"TRN","destination":"KZN","bestDeparture":"2026-08-06","bestBooking":"2026-07-21","priceBase":459,"low":169,"lowDate":"2026-06-02","dropAbs":0,"dropPct":0,"currency":"EUR","airline":"","confidence":"high","book":"https://tp.media/r?marker=730427&trs=531148&p=4114&u=https%3A%2F%2Fwww.aviasales.com%2Fsearch%2FTRN0608KZN1&campaign_id=100","updated":"2026-07-21T05:41:32.858Z"},"KEJ":{"origin":"TRN","destination":"KEJ","bestDeparture":"2026-07-23","bestBooking":"2026-07-21","priceBase":482,"low":481,"lowDate":"2026-07-19","dropAbs":0,"dropPct":0,"currency":"EUR","airline":"","confidence":"high","book":"https://tp.media/r?marker=730427&trs=531148&p=4114&u=https%3A%2F%2Fwww.aviasales.com%2Fsearch%2FTRN2307KEJ1&campaign_id=100","updated":"2026-07-21T05:41:32.858Z"},"AGB":{"origin":"TRN","destination":"AGB","bestDeparture":"2026-07-27","bestBooking":"2026-07-21","priceBase":510,"low":510,"lowDate":"2026-07-21","dropAbs":0,"dropPct":0,"currency":"EUR","airline":"","confidence":"high","book":"https://tp.media/r?marker=730427&trs=531148&p=4114&u=https%3A%2F%2Fwww.aviasales.com%2Fsearch%2FTRN2707AGB1&campaign_id=100","updated":"2026-07-21T05:41:32.858Z"},"UFA":{"origin":"TRN","destination":"UFA","bestDeparture":"2026-08-09","bestBooking":"2026-07-21","priceBase":597,"low":597,"lowDate":"2026-07-21","dropAbs":0,"dropPct":0,"currency":"EUR","airline":"","confidence":"high","book":"https://tp.media/r?marker=730427&trs=531148&p=4114&u=https%3A%2F%2Fwww.aviasales.com%2Fsearch%2FTRN0908UFA1&campaign_id=100","updated":"2026-07-21T05:41:32.858Z"},"AUS":{"origin":"TRN","destination":"AUS","bestDeparture":"2026-08-18","bestBooking":"2026-07-21","priceBase":614,"low":612,"lowDate":"2026-07-18","dropAbs":0,"dropPct":0,"currency":"EUR","airline":"","confidence":"high","book":"https://tp.media/r?marker=730427&trs=531148&p=4114&u=https%3A%2F%2Fwww.aviasales.com%2Fsearch%2FTRN1808AUS1&campaign_id=100","updated":"2026-07-21T05:41:32.858Z"},"SYD":{"origin":"TRN","destination":"SYD","bestDeparture":"2026-10-22","bestBooking":"2026-07-21","priceBase":616,"low":614,"lowDate":"2026-07-18","dropAbs":0,"dropPct":0,"currency":"EUR","airline":"","confidence":"high","book":"https://tp.media/r?marker=730427&trs=531148&p=4114&u=https%3A%2F%2Fwww.aviasales.com%2Fsearch%2FTRN2210SYD1&campaign_id=100","updated":"2026-07-21T05:41:32.858Z"},"FNA":{"origin":"TRN","destination":"FNA","bestDeparture":"2027-01-09","bestBooking":"2026-07-21","priceBase":618,"low":443,"lowDate":"2026-07-02","dropAbs":0,"dropPct":0,"currency":"EUR","airline":"","confidence":"high","book":"https://tp.media/r?marker=730427&trs=531148&p=4114&u=https%3A%2F%2Fwww.aviasales.com%2Fsearch%2FTRN0901FNA1&campaign_id=100","updated":"2026-07-21T05:41:32.858Z"},"HKT":{"origin":"TRN","destination":"HKT","bestDeparture":"2026-12-25","bestBooking":"2026-07-21","priceBase":626,"low":624,"lowDate":"2026-07-18","dropAbs":0,"dropPct":0,"currency":"EUR","airline":"","confidence":"high","book":"https://tp.media/r?marker=730427&trs=531148&p=4114&u=https%3A%2F%2Fwww.aviasales.com%2Fsearch%2FTRN2512HKT1&campaign_id=100","updated":"2026-07-21T05:41:32.858Z"},"MCX":{"origin":"TRN","destination":"MCX","bestDeparture":"2026-08-10","bestBooking":"2026-07-21","priceBase":819,"low":816,"lowDate":"2026-07-18","dropAbs":0,"dropPct":0,"currency":"EUR","airline":"","confidence":"high","book":"https://tp.media/r?marker=730427&trs=531148&p=4114&u=https%3A%2F%2Fwww.aviasales.com%2Fsearch%2FTRN1008MCX1&campaign_id=100","updated":"2026-07-21T05:41:32.858Z"},"MSQ":{"origin":"TRN","destination":"MSQ","bestDeparture":"2026-07-30","bestBooking":"2026-07-21","priceBase":862,"low":288,"lowDate":"2026-06-10","dropAbs":0,"dropPct":0,"currency":"EUR","airline":"","confidence":"high","book":"https://tp.media/r?marker=730427&trs=531148&p=4114&u=https%3A%2F%2Fwww.aviasales.com%2Fsearch%2FTRN3007MSQ1&campaign_id=100","updated":"2026-07-21T05:41:32.858Z"},"BZE":{"origin":"TRN","destination":"BZE","bestDeparture":"2026-07-30","bestBooking":"2026-07-21","priceBase":934,"low":934,"lowDate":"2026-07-21","dropAbs":0,"dropPct":0,"currency":"EUR","airline":"","confidence":"high","book":"https://tp.media/r?marker=730427&trs=531148&p=4114&u=https%3A%2F%2Fwww.aviasales.com%2Fsearch%2FTRN3007BZE1&campaign_id=100","updated":"2026-07-21T05:41:32.858Z"},"WLG":{"origin":"TRN","destination":"WLG","bestDeparture":"2027-06-12","bestBooking":"2026-07-21","priceBase":962,"low":959,"lowDate":"2026-07-19","dropAbs":0,"dropPct":0,"currency":"EUR","airline":"","confidence":"high","book":"https://tp.media/r?marker=730427&trs=531148&p=4114&u=https%3A%2F%2Fwww.aviasales.com%2Fsearch%2FTRN1206WLG1&campaign_id=100","updated":"2026-07-21T05:41:32.858Z"},"IPN":{"origin":"TRN","destination":"IPN","bestDeparture":"2026-07-31","bestBooking":"2026-07-21","priceBase":1634,"low":1634,"lowDate":"2026-07-21","dropAbs":0,"dropPct":0,"currency":"EUR","airline":"","confidence":"high","book":"https://tp.media/r?marker=730427&trs=531148&p=4114&u=https%3A%2F%2Fwww.aviasales.com%2Fsearch%2FTRN3107IPN1&campaign_id=100","updated":"2026-07-21T05:41:32.858Z"}}}