{"origin":"YQG","generated":"2026-07-18T05:19:27.999Z","count":5,"routes":{"YTO":{"origin":"YQG","destination":"YTO","bestDeparture":"2026-07-25","bestBooking":"2026-07-18","priceBase":184,"low":184,"lowDate":"2026-07-14","dropAbs":0,"dropPct":0,"currency":"EUR","airline":"","confidence":"high","book":"https://tp.media/r?marker=730427&trs=531148&p=4114&u=https%3A%2F%2Fwww.aviasales.com%2Fsearch%2FYQG2507YTO1&campaign_id=100","updated":"2026-07-18T05:19:27.999Z"},"YOW":{"origin":"YQG","destination":"YOW","bestDeparture":"2026-07-26","bestBooking":"2026-07-18","priceBase":187,"low":187,"lowDate":"2026-07-18","dropAbs":1,"dropPct":1,"currency":"EUR","airline":"","confidence":"high","book":"https://tp.media/r?marker=730427&trs=531148&p=4114&u=https%3A%2F%2Fwww.aviasales.com%2Fsearch%2FYQG2607YOW1&campaign_id=100","updated":"2026-07-18T05:19:27.999Z"},"YKF":{"origin":"YQG","destination":"YKF","bestDeparture":"2026-07-27","bestBooking":"2026-07-18","priceBase":217,"low":217,"lowDate":"2026-07-18","dropAbs":0,"dropPct":0,"currency":"EUR","airline":"","confidence":"high","book":"https://tp.media/r?marker=730427&trs=531148&p=4114&u=https%3A%2F%2Fwww.aviasales.com%2Fsearch%2FYQG2707YKF1&campaign_id=100","updated":"2026-07-18T05:19:27.999Z"},"MAN":{"origin":"YQG","destination":"MAN","bestDeparture":"2026-07-26","bestBooking":"2026-07-18","priceBase":433,"low":433,"lowDate":"2026-07-18","dropAbs":2,"dropPct":0,"currency":"EUR","airline":"","confidence":"high","book":"https://tp.media/r?marker=730427&trs=531148&p=4114&u=https%3A%2F%2Fwww.aviasales.com%2Fsearch%2FYQG2607MAN1&campaign_id=100","updated":"2026-07-18T05:19:27.999Z"},"ZCL":{"origin":"YQG","destination":"ZCL","bestDeparture":"2026-07-23","bestBooking":"2026-07-18","priceBase":656,"low":656,"lowDate":"2026-07-18","dropAbs":1,"dropPct":0,"currency":"EUR","airline":"","confidence":"high","book":"https://tp.media/r?marker=730427&trs=531148&p=4114&u=https%3A%2F%2Fwww.aviasales.com%2Fsearch%2FYQG2307ZCL1&campaign_id=100","updated":"2026-07-18T05:19:27.999Z"}}}